Workbook

Sheet 5.ID
A1: Do Not Alter or Delete this Worksheet or you submission cannot be graded! | E1: DirVer
A2: Action | B2: Name | C2: Panther ID | D2: Date/Time | E2: S01
A3: Start S01 | B3: Ahadu Solomon | C3: 202020202 | D3: 44459.23 | E3: Microsoft Office User
A4: Starter Sheet | B4: None | C4: 0 | D4: 43831
E5: Welcome to Microsoft Excel version 16.53 build 912 running on Macintosh (Intel) Version 11.2.3 (Build 20D91)!

Sheet Pivot Table and Chart Pt1
A1: Month | B1: Demand
A2: 43831 | B2: 2323 | D2: Sum of Demand | E2: Column Labels | P2: 1. Copy your data set to columns A and B, leave the labels
A3: 43862 | B3: 2804 | D3: Row Labels | E3: 2020 | F3: 2021 | G3: 2022 | H3: Grand Total | P3: 2. Create a pivot table selecting Existing Worksheet at location D2
A4: 43891 | B4: 2469 | D4: Jan | E4: 2323 | F4: 2429 | G4: 2712 | H4: 7464 | P4: 3. Confirm that there is no data from earlier than Jan 2019, and then remove that line
A5: 43922 | B5: 3278 | D5: Feb | E5: 2804 | F5: 2495 | G5: 3229 | H5: 8528 | P5: 4. Create a Pivot Graph that looks like the one given in the Project instructions on Csepub
A6: 43952 | B6: 3617 | D6: Mar | E6: 2469 | F6: 2595 | G6: 3077 | H6: 8141 | P6: 5. Insert the trend line for 2022 and include the equation
A7: 43983 | B7: 2669 | D7: Apr | E7: 3278 | F7: 3383 | G7: 3646 | H7: 10307
A8: 44013 | B8: 2010 | D8: May | E8: 3617 | F8: 3426 | G8: 3998 | H8: 11041
A9: 44044 | B9: 2715 | D9: Jun | E9: 2669 | F9: 3654 | G9: 4062 | H9: 10385
A10: 44075 | B10: 2890 | D10: Jul | E10: 2010 | F10: 2629 | G10: 3171 | H10: 7810
A11: 44105 | B11: 2973 | D11: Aug | E11: 2715 | F11: 2996 | G11: 3638 | H11: 9349
A12: 44136 | B12: 3485 | D12: Sep | E12: 2890 | F12: 3150 | G12: 3623 | H12: 9663
A13: 44166 | B13: 4548 | D13: Oct | E13: 2973 | F13: 3924 | G13: 4050 | H13: 10947
A14: 44197 | B14: 2429 | D14: Nov | E14: 3485 | F14: 4185 | G14: 4528 | H14: 12198
A15: 44228 | B15: 2495 | D15: Dec | E15: 4548 | F15: 4982 | G15: 5702 | H15: 15232
A16: 44256 | B16: 2595 | D16: Grand Total | E16: 35781 | F16: 39848 | G16: 45436 | H16: 121065
A17: 44287 | B17: 3383
A18: 44317 | B18: 3426
A19: 44348 | B19: 3654
A20: 44378 | B20: 2629
A21: 44409 | B21: 2996
A22: 44440 | B22: 3150
A23: 44470 | B23: 3924
A24: 44501 | B24: 4185
A25: 44531 | B25: 4982
A26: 44562 | B26: 2712
A27: 44593 | B27: 3229
A28: 44621 | B28: 3077
... A37: 44896 | B37: 5702

Sheet SI and regression Pt 2
A1: Month | B1: Demand | C1: Monthly average by Year (demand w/out Seasonality | D1: Seasonal Index | E1: 3 year Average SI | F1: Deseasonalized | G1: Time period | J1: Regression Output
A2: 43831 | B2: =GETPIVOTDATA("Demand",'Pivot Table and Chart Pt1'!$D$2,"Months (Month)",1,"Years (Month)",2020) -> 2323 | D2: =B2/$C$13 -> 0.77907269 | E2: =AVERAGE(D2,D14,D26) -> 0.74227085 | F2: =B2/E2 -> 3129.5854 | G2: 1 | I2: CLICK CELL J2 as output cell for regression | J2: SUMMARY OUTPUT
A3: 43862 | B3: =GETPIVOTDATA("Demand",'Pivot Table and Chart Pt1'!$D$2,"Months (Month)",2,"Years (Month)",2020) -> 2804 | D3: =B3/$C$13 -> 0.94038736 | E3: =AVERAGE(D3,D15,D27) -> 0.84818215 | F3: =B3/E3 -> 3305.8937 | G3: 2
A4: 43891 | B4: =GETPIVOTDATA("Demand",'Pivot Table and Chart Pt1'!$D$2,"Months (Month)",3,"Years (Month)",2020) -> 2469 | D4: =B4/$C$13 -> 0.82803723 | E4: =AVERAGE(D4,D16,D28) -> 0.80738879 | F4: =B4/E4 -> 3058.0063 | G4: 3 | J4: Regression Statistics
A5: 43922 | B5: =GETPIVOTDATA("Demand",'Pivot Table and Chart Pt1'!$D$2,"Months (Month)",4,"Years (Month)",2020) -> 3278 | D5: =B5/$C$13 -> 1.0993544 | E5: =AVERAGE(D5,D17,D29) -> 1.0270209 | F5: =B5/E5 -> 3191.756 | G5: 4 | J5: Multiple R | K5: 0.82084274
A6: 43952 | B6: =GETPIVOTDATA("Demand",'Pivot Table and Chart Pt1'!$D$2,"Months (Month)",5,"Years (Month)",2020) -> 3617 | D6: =B6/$C$13 -> 1.213046 | E6: =AVERAGE(D6,D18,D30) -> 1.1002231 | F6: =B6/E6 -> 3287.515 | G6: 5 | J6: R Square | K6: 0.6737828
A7: 43983 | B7: =GETPIVOTDATA("Demand",'Pivot Table and Chart Pt1'!$D$2,"Months (Month)",6,"Years (Month)",2020) -> 2669 | D7: =B7/$C$13 -> 0.89511193 | E7: =AVERAGE(D7,D19,D31) -> 1.0227664 | F7: =B7/E7 -> 2609.5891 | G7: 6 | J7: Adjusted R Square | K7: 0.66418818
A8: 44013 | B8: =GETPIVOTDATA("Demand",'Pivot Table and Chart Pt1'!$D$2,"Months (Month)",7,"Years (Month)",2020) -> 2010 | D8: =B8/$C$13 -> 0.67410078 | E8: =AVERAGE(D8,D20,D32) -> 0.76776499 | F8: =B8/E8 -> 2617.9886 | G8: 7 | J8: Standard Error | K8: 225.11471
A9: 44044 | B9: =GETPIVOTDATA("Demand",'Pivot Table and Chart Pt1'!$D$2,"Months (Month)",8,"Years (Month)",2020) -> 2715 | D9: =B9/$C$13 -> 0.91053911 | E9: =AVERAGE(D9,D21,D33) -> 0.92453053 | F9: =B9/E9 -> 2936.6256 | G9: 8 | J9: Observations | K9: 36
A10: 44075 | B10: =GETPIVOTDATA("Demand",'Pivot Table and Chart Pt1'!$D$2,"Months (Month)",9,"Years (Month)",2020) -> 2890 | D10: =B10/$C$13 -> 0.96922948 | E10: =AVERAGE(D10,D22,D34) -> 0.95823219 | F10: =B10/E10 -> 3015.9705 | G10: 9
A11: 44105 | B11: =GETPIVOTDATA("Demand",'Pivot Table and Chart Pt1'!$D$2,"Months (Month)",10,"Years (Month)",2020) -> 2973 | D11: =B11/$C$13 -> 0.99706548 | E11: =AVERAGE(D11,D23,D35) -> 1.0827974 | F11: =B11/E11 -> 2745.6659 | G11: 10 | J11: ANOVA
A12: 44136 | B12: =GETPIVOTDATA("Demand",'Pivot Table and Chart Pt1'!$D$2,"Months (Month)",11,"Years (Month)",2020) -> 3485 | D12: =B12/$C$13 -> 1.1687767 | E12: =AVERAGE(D12,D24,D36) -> 1.2083152 | F12: =B12/E12 -> 2884.1811 | G12: 11 | K12: df | L12: SS | M12: MS | N12: F | O12: Significance F
A13: 44166 | B13: =GETPIVOTDATA("Demand",'Pivot Table and Chart Pt1'!$D$2,"Months (Month)",12,"Years (Month)",2020) -> 4548 | C13: =AVERAGE(B2:B13) -> 2981.75 | D13: =B13/$C$13 -> 1.5252788 | E13: =AVERAGE(D13,D25,D37) -> 1.5105074 | F13: =B13/E13 -> 3010.9087 | G13: 12 | J13: Regression | K13: 1 | L13: 3558768.6 | M13: 3558768.6 | N13: 70.225039 | O13: 8.7638991e-10
A14: 44197 | B14: =GETPIVOTDATA("Demand",'Pivot Table and Chart Pt1'!$D$2,"Months (Month)",1,"Years (Month)",2021) -> 2429 | D14: =B14/$C$25 -> 0.73147962 | F14: =B14/E2 -> 3272.3904 | G14: 13 | J14: Residual | K14: 34 | L14: 1723005.5 | M14: 50676.633
A15: 44228 | B15: =GETPIVOTDATA("Demand",'Pivot Table and Chart Pt1'!$D$2,"Months (Month)",2,"Years (Month)",2021) -> 2495 | D15: =B15/$C$25 -> 0.75135515 | F15: =B15/E3 -> 2941.5851 | G15: 14 | J15: Total | K15: 35 | L15: 5281774.1
A16: 44256 | B16: =GETPIVOTDATA("Demand",'Pivot Table and Chart Pt1'!$D$2,"Months (Month)",3,"Years (Month)",2021) -> 2595 | D16: =B16/$C$25 -> 0.78146958 | F16: =B16/E4 -> 3214.0649 | G16: 15
A17: 44287 | B17: =GETPIVOTDATA("Demand",'Pivot Table and Chart Pt1'!$D$2,"Months (Month)",4,"Years (Month)",2021) -> 3383 | D17: =B17/$C$25 -> 1.0187713 | F17: =B17/E5 -> 3293.9934 | G17: 16 | K17: Coefficients | L17: Standard Error | M17: t Stat | N17: P-value | O17: Lower 95% | P17: Upper 95% | Q17: Lower 95.0% | R17: Upper 95.0%
A18: 44317 | B18: =GETPIVOTDATA("Demand",'Pivot Table and Chart Pt1'!$D$2,"Months (Month)",5,"Years (Month)",2021) -> 3426 | D18: =B18/$C$25 -> 1.0317205 | F18: =B18/E6 -> 3113.9138 | G18: 17 | J18: Intercept | K18: 2803.2973 | L18: 76.629331 | M18: 36.582563 | N18: 6.8666329e-29 | O18: 2647.5678 | P18: 2959.0268 | Q18: 2647.5678 | R18: 2959.0268
A19: 44348 | B19: =GETPIVOTDATA("Demand",'Pivot Table and Chart Pt1'!$D$2,"Months (Month)",6,"Years (Month)",2021) -> 3654 | D19: =B19/$C$25 -> 1.1003814 | F19: =B19/E7 -> 3572.6635 | G19: 18 | J19: X Variable 1 | K19: 30.265954 | L19: 3.6116725 | M19: 8.3800381 | N19: 8.7638991e-10 | O19: 22.926152 | P19: 37.605755 | Q19: 22.926152 | R19: 37.605755
A20: 44378 | B20: =GETPIVOTDATA("Demand",'Pivot Table and Chart Pt1'!$D$2,"Months (Month)",7,"Years (Month)",2021) -> 2629 | D20: =B20/$C$25 -> 0.79170849 | F20: =B20/E8 -> 3424.2249 | G20: 19
A21: 44409 | B21: =GETPIVOTDATA("Demand",'Pivot Table and Chart Pt1'!$D$2,"Months (Month)",8,"Years (Month)",2021) -> 2996 | D21: =B21/$C$25 -> 0.90222847 | F21: =B21/E9 -> 3240.5636 | G21: 20
A22: 44440 | B22: =GETPIVOTDATA("Demand",'Pivot Table and Chart Pt1'!$D$2,"Months (Month)",9,"Years (Month)",2021) -> 3150 | D22: =B22/$C$25 -> 0.9486047 | F22: =B22/E10 -> 3287.3035 | G22: 21
A23: 44470 | B23: =GETPIVOTDATA("Demand",'Pivot Table and Chart Pt1'!$D$2,"Months (Month)",10,"Years (Month)",2021) -> 3924 | D23: =B23/$C$25 -> 1.1816904 | F23: =B23/E11 -> 3623.9465 | G23: 22
A24: 44501 | B24: =GETPIVOTDATA("Demand",'Pivot Table and Chart Pt1'!$D$2,"Months (Month)",11,"Years (Month)",2021) -> 4185 | D24: =B24/$C$25 -> 1.2602891 | F24: =B24/E12 -> 3463.5001 | G24: 23
A25: 44531 | B25: =GETPIVOTDATA("Demand",'Pivot Table and Chart Pt1'!$D$2,"Months (Month)",12,"Years (Month)",2021) -> 4982 | C25: =AVERAGE(B14:B25) -> 3320.6667 | D25: =B25/$C$25 -> 1.5003011 | F25: =B25/E13 -> 3298.2293 | G25: 24
A26: 44562 | B26: =GETPIVOTDATA("Demand",'Pivot Table and Chart Pt1'!$D$2,"Months (Month)",1,"Years (Month)",2022) -> 2712 | D26: =B26/$C$37 -> 0.71626023 | F26: =B26/E2 -> 3653.6528 | G26: 25
A27: 44593 | B27: =GETPIVOTDATA("Demand",'Pivot Table and Chart Pt1'!$D$2,"Months (Month)",2,"Years (Month)",2022) -> 3229 | D27: =B27/$C$37 -> 0.85280394 | F27: =B27/E3 -> 3806.9653 | G27: 26
A28: 44621 | B28: =GETPIVOTDATA("Demand",'Pivot Table and Chart Pt1'!$D$2,"Months (Month)",3,"Years (Month)",2022) -> 3077 | D28: =B28/$C$37 -> 0.81265957 | F28: =B28/E4 -> 3811.0512 | G28: 27
A29: 44652 | B29: =GETPIVOTDATA("Demand",'Pivot Table and Chart Pt1'!$D$2,"Months (Month)",4,"Years (Month)",2022) -> 3646 | D29: =B29/$C$37 -> 0.96293688 | F29: =B29/E5 -> 3550.0739 | G29: 28
A30: 44682 | B30: =GETPIVOTDATA("Demand",'Pivot Table and Chart Pt1'!$D$2,"Months (Month)",5,"Years (Month)",2022) -> 3998 | D30: =B30/$C$37 -> 1.0559028 | F30: =B30/E6 -> 3633.8084 | G30: 29
A31: 44713 | B31: =GETPIVOTDATA("Demand",'Pivot Table and Chart Pt1'!$D$2,"Months (Month)",6,"Years (Month)",2022) -> 4062 | D31: =B31/$C$37 -> 1.0728057 | F31: =B31/E7 -> 3971.5815 | G31: 30
A32: 44743 | B32: =GETPIVOTDATA("Demand",'Pivot Table and Chart Pt1'!$D$2,"Months (Month)",7,"Years (Month)",2022) -> 3171 | D32: =B32/$C$37 -> 0.83748569 | F32: =B32/E8 -> 4130.1701 | G32: 31
A33: 44774 | B33: =GETPIVOTDATA("Demand",'Pivot Table and Chart Pt1'!$D$2,"Months (Month)",8,"Years (Month)",2022) -> 3638 | D33: =B33/$C$37 -> 0.96082402 | F33: =B33/E9 -> 3934.9701 | G33: 32
A34: 44805 | B34: =GETPIVOTDATA("Demand",'Pivot Table and Chart Pt1'!$D$2,"Months (Month)",9,"Years (Month)",2022) -> 3623 | D34: =B34/$C$37 -> 0.9568624 | F34: =B34/E10 -> 3780.9208 | G34: 33
A35: 44835 | B35: =GETPIVOTDATA("Demand",'Pivot Table and Chart Pt1'!$D$2,"Months (Month)",10,"Years (Month)",2022) -> 4050 | D35: =B35/$C$37 -> 1.0696364 | F35: =B35/E11 -> 3740.3118 | G35: 34
A36: 44866 | B36: =GETPIVOTDATA("Demand",'Pivot Table and Chart Pt1'!$D$2,"Months (Month)",11,"Years (Month)",2022) -> 4528 | D36: =B36/$C$37 -> 1.1958799 | F36: =B36/E12 -> 3747.3664 | G36: 35 | H36: The below 2 columns are for the forecast for 2023
A37: 44896 | B37: =GETPIVOTDATA("Demand",'Pivot Table and Chart Pt1'!$D$2,"Months (Month)",12,"Years (Month)",2022) -> 5702 | C37: =AVERAGE(B26:B37) -> 3786.3333 | D37: =B37/$C$37 -> 1.5059424 | F37: =B37/E13 -> 3774.8904 | G37: 36 | H37: Deseasonalized forecast | I37: Seasonalized forecast, Use the average seasonal Index
B38: This space will be left blank. | G38: 37 | H38: =$K$19*G38+$K$18 -> 3923.1376 | I38: =H38*E2 -> 2912.0307
G39: 38 | H39: =$K$19*G39+$K$18 -> 3953.4035 | I39: =H39*E3 -> 3353.2063
B40: For the C and E columns above, only the blue boxes are needed | G40: 39 | H40: =$K$19*G40+$K$18 -> 3983.6695 | I40: =H40*E4 -> 3216.3701
G41: 40 | H41: =$K$19*G41+$K$18 -> 4013.9354 | I41: =H41*E5 -> 4122.3955
G42: 41 | H42: =$K$19*G42+$K$18 -> 4044.2014 | I42: =H42*E6 -> 4449.5239
G43: 42 | H43: =$K$19*G43+$K$18 -> 4074.4673 | I43: =H43*E7 -> 4167.2281
G44: 43 | H44: =$K$19*G44+$K$18 -> 4104.7333 | I44: =H44*E8 -> 3151.4705
G45: 44 | H45: =$K$19*G45+$K$18 -> 4134.9992 | I45: =H45*E9 -> 3822.9331
G46: 45 | H46: =$K$19*G46+$K$18 -> 4165.2652 | I46: =H46*E10 -> 3991.2912
G47: 46 | H47: =$K$19*G47+$K$18 -> 4195.5312 | I47: =H47*E11 -> 4542.9104
G48: 47 | H48: =$K$19*G48+$K$18 -> 4225.7971 | I48: =H48*E12 -> 5106.0951
G49: 48 | H49: =$K$19*G49+$K$18 -> 4256.0631 | I49: =H49*E13 -> 6428.815
C50: Highest monthly average | E50: Highest Average SI | F50: Total 3 year deseasonalized demand | H50: Put average of monthly seasonalized forcast in cell I50 | I50: =AVERAGE(I38:I49) -> 4105.3558
C51: =C37 -> 3786.3333 | E51: =E13 -> 1.5105074 | F51: =SUM(F2:F37) -> 121075.83 | H51: When you move your forecast to the profit models, you must use an equation, not just copy the values
C52: Total 3 year demand | F52: Average 3 year deseasonalized demand
C53: =SUM(B2:B37) -> 121065 | F53: =AVERAGE(F2:F37) -> 3363.2174
C54: Average Monthly demand using the 3 year demand
C55: =AVERAGE(C13,C25,C37) -> 3362.9167
Z100: Ahadu Solomon
Z102: Spring 2021

Sheet Food Truck Demand
A1: Month | B1: Demand | C1: Hours operating/week | D1: Event location | E1: office location | H1: Demand is based off multiple regression
A2: 44470 | B2: 3634 | C2: 30 | D2: 1 | E2: 0 | H2: Use the data to the left from 10/2021 till 1/2023 to create a regression model
A3: 44501 | B3: 4550 | C3: 40 | D3: 0 | E3: 1 | H3: Use the model and the data in the blue box to create the demand for 2023
A4: 44531 | B4: 5330 | C4: 55 | D4: 1 | E4: 0
A5: 44562 | B5: 3100 | C5: 30 | D5: 0 | E5: 1 | H5: Event and office location are dummy variables.
A6: 44593 | B6: 2999 | C6: 30 | D6: 0 | E6: 1 | H6: Since these are the only 2 possible locations. This means that if they aren't at an Event location, they will be at an office location.
A7: 44621 | B7: 3051 | C7: 35 | D7: 1 | E7: 0 | H7: Therefore you only need to use 1 ( such as just the Event column) in the Regression, since by default a 0 in the event column means they are at an office location.
A8: 44652 | B8: 3753 | C8: 35 | D8: 0 | E8: 1
A9: 44682 | B9: 3709 | C9: 35 | D9: 0 | E9: 1
A10: 44713 | B10: 3930 | C10: 40 | D10: 1 | E10: 0
A11: 44743 | B11: 2949 | C11: 40 | D11: 0 | E11: 1
A12: 44774 | B12: 3348 | C12: 45 | D12: 0 | E12: 1
A13: 44805 | B13: 3400 | C13: 40 | D13: 0 | E13: 1
A14: 44835 | B14: 4400 | C14: 55 | D14: 1 | E14: 0
A15: 44866 | B15: 5079 | C15: 55 | D15: 1 | E15: 0
A16: 44896 | B16: 6087 | C16: 60 | D16: 1 | E16: 0
A17: 44927 | B17: =$L$39*C17+$L$40*D17+$L$38 -> 1949.7956 | C17: 15 | D17: 0 | E17: 1 | H17: This Blue box represent the variables to use in the regression equation to predict the demand for 2023.
A18: 44958 | B18: =$L$39*C18+$L$40*D18+$L$38 -> 2298.6423 | C18: 20 | D18: 0 | E18: 1
A19: 44986 | B19: =$L$39*C19+$L$40*D19+$L$38 -> 2298.6423 | C19: 20 | D19: 0 | E19: 1
A20: 45017 | B20: =$L$39*C20+$L$40*D20+$L$38 -> 2647.4891 | C20: 25 | D20: 0 | E20: 1
A21: 45047 | B21: =$L$39*C21+$L$40*D21+$L$38 -> 2647.4891 | C21: 25 | D21: 0 | E21: 1
A22: 45078 | B22: =$L$39*C22+$L$40*D22+$L$38 -> 3654.3723 | C22: 35 | D22: 1 | E22: 0 | K22: SUMMARY OUTPUT
A23: 45108 | B23: =$L$39*C23+$L$40*D23+$L$38 -> 3654.3723 | C23: 35 | D23: 1 | E23: 0
A24: 45139 | B24: =$L$39*C24+$L$40*D24+$L$38 -> 2647.4891 | C24: 25 | D24: 0 | E24: 1 | K24: Regression Statistics
A25: 45170 | B25: =$L$39*C25+$L$40*D25+$L$38 -> 2996.3358 | C25: 30 | D25: 0 | E25: 1 | K25: Multiple R | L25: 0.84434541
A26: 45200 | B26: =$L$39*C26+$L$40*D26+$L$38 -> 4003.219 | C26: 40 | D26: 1 | E26: 0 | K26: R Square | L26: 0.71291916
A27: 45231 | B27: =$L$39*C27+$L$40*D27+$L$38 -> 4003.219 | C27: 40 | D27: 1 | E27: 0 | K27: Adjusted R Square | L27: 0.66507236
A28: 45261 | B28: =$L$39*C28+$L$40*D28+$L$38 -> 4352.0657 | C28: 45 | D28: 1 | E28: 0 | K28: Standard Error | L28: 549.18651
K29: Observations | L29: 15
K31: ANOVA
L32: df | M32: SS | N32: MS | O32: F | P32: Significance F
K33: Regression | L33: 2 | M33: 8987875.7 | N33: 4493937.9 | O33: 14.900037 | P33: 0.0005597901
K34: Residual | L34: 12 | M34: 3619269.9 | N34: 301605.82
K35: Total | L35: 14 | M35: 12607146
L37: Coefficients | M37: Standard Error | N37: t Stat | O37: P-value | P37: Lower 95% | Q37: Upper 95% | R37: Lower 95.0% | S37: Upper 95.0%
K38: Intercept | L38: 903.25547 | M38: 657.37506 | N38: 1.3740337 | O38: 0.19455225 | P38: -529.04173 | Q38: 2335.5527 | R38: -529.04173 | S38: 2335.5527
K39: Hours operating/week | L39: 69.769343 | M39: 17.031744 | N39: 4.0964297 | O39: 0.0014817974 | P39: 32.66036 | Q39: 106.87833 | R39: 32.66036 | S39: 106.87833
K40: Event location | L40: 309.18978 | M40: 333.72162 | N40: 0.92649011 | O40: 0.37245001 | P40: -417.92717 | Q40: 1036.3067 | R40: -417.92717 | S40: 1036.3067

Sheet Financial information  FT
A1: Donut Information for Food Truck
A2: Based on the below data, create the profit model for Donuts to Go.
A3: Assume that each customer will buy one donut and one cup of coffee
I4: Row Labels | J4: Sum of Expense/revenue FT
C5: new | D5: Drop Production since flexible hours and limited storage space | I5: Fixed Expense | J5: 5045
A6: Item | B6: Profit Model label | C6: Expense/revenue FT | I6: Rev: Coffee | J6: 2.99
A7: Revenue: Cup of Coffee | B7: Rev: Coffee | C7: 2.99 | I7: Rev: Donut | J7: 2.5
A8: Revenue: Donut | B8: Rev: Donut | C8: 2.5 | I8: Variable Expense coffee | J8: 0.5
A9: Donut ingredients per donunt) | B9: Variable Expense donut | C9: 0.5 | I9: Variable Expense donut | J9: 0.6
A10: paper products: napkins, plates etc per Donut | B10: Variable Expense donut | C10: 0.1 | I10: Grand Total | J10: 5051.59
A11: Insurance | B11: Fixed Expense | C11: 150
A12: Maintenance & Repairs to equipment | B12: Fixed Expense | C12: 300
A13: Marketing & Promotion: Advertising | B13: Fixed Expense | C13: 0 | D13: No advertising, Friend doing locations on Insta and Facebook
A14: Coffee | B14: Variable Expense coffee | C14: 0.35
A15: Coffee cups | B15: Variable Expense coffee | C15: 0.15
A16: Payroll: Wages (Owner/ Manager) | B16: Fixed Expense | C16: 2400
A17: Payroll: Wages (per Employees) | B17: Fixed Expense | C17: 0 | D17: No other employees
A18: Donut and Coffee equipment rent | B18: Fixed Expense | C18: 0
A19: Professional Fees: Accounting | B19: Fixed Expense | C19: 50
A20: Professional Fees: Legal | B20: Fixed Expense | C20: 25
A21: Powdered and Liquid Beverages | B21: Fixed Expense | C21: 0
A22: Rent | B22: Fixed Expense | C22: 2120 | D22: No rent instead payment for lease on Food Truck.
A23: Supplies: Office | B23: Fixed Expense | C23: 0
A24: Utilities | B24: Fixed Expense | C24: 0
A30: Additional Data
A31: Food Truck
A32: Monthly Production | B32: make to order
A33: Lost Sales
A34: Day old revenue
A35: High demand, % above Average | B35: 0.05
A36: Low Demand, % below average | B36: 0.26
A62: Total

Sheet Franchise operations  Pt3
A1: FRANCHISE | B1: Reminder: Format Cells to show 2 decimal places | E1: Monthly Production | F1: Lost Sales | G1: Day old revenue
E2: ='Financial information 1 Pt1'!B31*(1+'Financial information 1 Pt1'!B38) -> 5280 | F2: ='Financial information 1 Pt1'!B32 -> 3 | G2: ='Financial information 1 Pt1'!B33 -> 1.25
A3: AVERAGE DEMAND
A4: Month | B4: 44927 | C4: 44958 | D4: 44986 | E4: 45017 | F4: 45047 | G4: 45078 | H4: 45108 | I4: 45139 | J4: 45170 | K4: 45200 | L4: 45231 | M4: 45261 | N4: Yearly Total
A5: Demand | B5: ='Current operations Pt3 '!B5*(1+'Financial information 1 Pt1'!$B$39) -> 3552.6774 | C5: ='Current operations Pt3 '!C5*(1+'Financial information 1 Pt1'!$B$39) -> 4090.9117 | D5: ='Current operations Pt3 '!D5*(1+'Financial information 1 Pt1'!$B$39) -> 3923.9715 | E5: ='Current operations Pt3 '!E5*(1+'Financial information 1 Pt1'!$B$39) -> 5029.3225 | F5: ='Current operations Pt3 '!F5*(1+'Financial information 1 Pt1'!$B$39) -> 5428.4191 | G5: ='Current operations Pt3 '!G5*(1+'Financial information 1 Pt1'!$B$39) -> 5084.0183 | H5: ='Current operations Pt3 '!H5*(1+'Financial information 1 Pt1'!$B$39) -> 3844.794 | I5: ='Current operations Pt3 '!I5*(1+'Financial information 1 Pt1'!$B$39) -> 4663.9783 | ... M5: ='Current operations Pt3 '!M5*(1+'Financial information 1 Pt1'!$B$39) -> 7843.1543 | N5: =SUM(B5:M5) -> 60102.409
A6: satisfied demand | B6: =MIN(B5,$E$2) -> 3552.6774 | C6: =MIN(C5,$E$2) -> 4090.9117 | D6: =MIN(D5,$E$2) -> 3923.9715 | E6: =MIN(E5,$E$2) -> 5029.3225 | F6: =MIN(F5,$E$2) -> 5280 | G6: =MIN(G5,$E$2) -> 5084.0183 | H6: =MIN(H5,$E$2) -> 3844.794 | I6: =MIN(I5,$E$2) -> 4663.9783 | ... M6: =MIN(M5,$E$2) -> 5280 | N6: =SUM(B6:M6) -> 56179.049
A7: Extra donuts(over) | B7: =IF(B5<$E$2,$E$2-B5,0) -> 1727.3226 | C7: =IF(C5<$E$2,$E$2-C5,0) -> 1189.0883 | D7: =IF(D5<$E$2,$E$2-D5,0) -> 1356.0285 | E7: =IF(E5<$E$2,$E$2-E5,0) -> 250.67753 | F7: =IF(F5<$E$2,$E$2-F5,0) -> 0 | G7: =IF(G5<$E$2,$E$2-G5,0) -> 195.98167 | H7: =IF(H5<$E$2,$E$2-H5,0) -> 1435.206 | I7: =IF(I5<$E$2,$E$2-I5,0) -> 616.02167 | ... M7: =IF(M5<$E$2,$E$2-M5,0) -> 0 | N7: =SUM(B7:M7) -> 7180.951
A8: Unsatisfied customers (short) | B8: =IF(B5>$E$2,B5-$E$2,0) -> 0 | C8: =IF(C5>$E$2,C5-$E$2,0) -> 0 | D8: =IF(D5>$E$2,D5-$E$2,0) -> 0 | E8: =IF(E5>$E$2,E5-$E$2,0) -> 0 | F8: =IF(F5>$E$2,F5-$E$2,0) -> 148.41915 | G8: =IF(G5>$E$2,G5-$E$2,0) -> 0 | H8: =IF(H5>$E$2,H5-$E$2,0) -> 0 | I8: =IF(I5>$E$2,I5-$E$2,0) -> 0 | ... M8: =IF(M5>$E$2,M5-$E$2,0) -> 2563.1543 | N8: =SUM(B8:M8) -> 3923.3601
A9: Revenue
A10: coffee | B10: =B6*'Financial information 1 Pt1'!$C$7 -> 10622.505 | C10: =C6*'Financial information 1 Pt1'!$C$7 -> 12231.826 | D10: =D6*'Financial information 1 Pt1'!$C$7 -> 11732.675 | E10: =E6*'Financial information 1 Pt1'!$C$7 -> 15037.674 | F10: =F6*'Financial information 1 Pt1'!$C$7 -> 15787.2 | G10: =G6*'Financial information 1 Pt1'!$C$7 -> 15201.215 | H10: =H6*'Financial information 1 Pt1'!$C$7 -> 11495.934 | I10: =I6*'Financial information 1 Pt1'!$C$7 -> 13945.295 | ... M10: =M6*'Financial information 1 Pt1'!$C$7 -> 15787.2 | N10: =SUM(B10:M10) -> 167975.36
A11: donut | B11: =B6*'Financial information 1 Pt1'!$C$8 -> 8881.6935 | C11: =C6*'Financial information 1 Pt1'!$C$8 -> 10227.279 | D11: =D6*'Financial information 1 Pt1'!$C$8 -> 9809.9288 | E11: =E6*'Financial information 1 Pt1'!$C$8 -> 12573.306 | F11: =F6*'Financial information 1 Pt1'!$C$8 -> 13200 | G11: =G6*'Financial information 1 Pt1'!$C$8 -> 12710.046 | H11: =H6*'Financial information 1 Pt1'!$C$8 -> 9611.9851 | I11: =I6*'Financial information 1 Pt1'!$C$8 -> 11659.946 | ... M11: =M6*'Financial information 1 Pt1'!$C$8 -> 13200 | N11: =SUM(B11:M11) -> 140447.62
A12: Revenue from day old sales | B12: =B7*$G$2 -> 2159.1532 | C12: =C7*$G$2 -> 1486.3604 | D12: =D7*$G$2 -> 1695.0356 | E12: =E7*$G$2 -> 313.34691 | F12: =F7*$G$2 -> 0 | G12: =G7*$G$2 -> 244.97709 | H12: =H7*$G$2 -> 1794.0075 | I12: =I7*$G$2 -> 770.02709 | ... M12: =M7*$G$2 -> 0 | N12: =SUM(B12:M12) -> 8976.1887
A13: Total Revenue | B13: =SUM(B10:B12) -> 21663.352 | C13: =SUM(C10:C12) -> 23945.466 | D13: =SUM(D10:D12) -> 23237.639 | E13: =SUM(E10:E12) -> 27924.327 | F13: =SUM(F10:F12) -> 28987.2 | G13: =SUM(G10:G12) -> 28156.238 | H13: =SUM(H10:H12) -> 22901.927 | I13: =SUM(I10:I12) -> 26375.268 | ... M13: =SUM(M10:M12) -> 28987.2 | N13: =SUM(B13:M13) -> 317399.17
A14: Expenses
A15: Fixed Expenses | B15: =GETPIVOTDATA("Expense/revenue",'Financial information 1 Pt1'!$E$5,"Profit Model label","Fixed Expense")+'Financial information 1 Pt1'!$B$37 -> 10150 | C15: =GETPIVOTDATA("Expense/revenue",'Financial information 1 Pt1'!$E$5,"Profit Model label","Fixed Expense")+'Financial information 1 Pt1'!$B$37 -> 10150 | D15: =GETPIVOTDATA("Expense/revenue",'Financial information 1 Pt1'!$E$5,"Profit Model label","Fixed Expense")+'Financial information 1 Pt1'!$B$37 -> 10150 | E15: =GETPIVOTDATA("Expense/revenue",'Financial information 1 Pt1'!$E$5,"Profit Model label","Fixed Expense")+'Financial information 1 Pt1'!$B$37 -> 10150 | F15: =GETPIVOTDATA("Expense/revenue",'Financial information 1 Pt1'!$E$5,"Profit Model label","Fixed Expense")+'Financial information 1 Pt1'!$B$37 -> 10150 | G15: =GETPIVOTDATA("Expense/revenue",'Financial information 1 Pt1'!$E$5,"Profit Model label","Fixed Expense")+'Financial information 1 Pt1'!$B$37 -> 10150 | H15: =GETPIVOTDATA("Expense/revenue",'Financial information 1 Pt1'!$E$5,"Profit Model label","Fixed Expense")+'Financial information 1 Pt1'!$B$37 -> 10150 | I15: =GETPIVOTDATA("Expense/revenue",'Financial information 1 Pt1'!$E$5,"Profit Model label","Fixed Expense")+'Financial information 1 Pt1'!$B$37 -> 10150 | ... M15: =GETPIVOTDATA("Expense/revenue",'Financial information 1 Pt1'!$E$5,"Profit Model label","Fixed Expense")+'Financial information 1 Pt1'!$B$37 -> 10150 | N15: =SUM(B15:M15) -> 121800
A16: Total Fixed Expense | B16: =GETPIVOTDATA("Expense/revenue",'Financial information 1 Pt1'!$E$5,"Profit Model label","Fixed Expense")+'Financial information 1 Pt1'!$B$37 -> 10150 | C16: =GETPIVOTDATA("Expense/revenue",'Financial information 1 Pt1'!$E$5,"Profit Model label","Fixed Expense")+'Financial information 1 Pt1'!$B$37 -> 10150 | D16: =GETPIVOTDATA("Expense/revenue",'Financial information 1 Pt1'!$E$5,"Profit Model label","Fixed Expense")+'Financial information 1 Pt1'!$B$37 -> 10150 | E16: =GETPIVOTDATA("Expense/revenue",'Financial information 1 Pt1'!$E$5,"Profit Model label","Fixed Expense")+'Financial information 1 Pt1'!$B$37 -> 10150 | F16: =GETPIVOTDATA("Expense/revenue",'Financial information 1 Pt1'!$E$5,"Profit Model label","Fixed Expense")+'Financial information 1 Pt1'!$B$37 -> 10150 | G16: =GETPIVOTDATA("Expense/revenue",'Financial information 1 Pt1'!$E$5,"Profit Model label","Fixed Expense")+'Financial information 1 Pt1'!$B$37 -> 10150 | H16: =GETPIVOTDATA("Expense/revenue",'Financial information 1 Pt1'!$E$5,"Profit Model label","Fixed Expense")+'Financial information 1 Pt1'!$B$37 -> 10150 | I16: =GETPIVOTDATA("Expense/revenue",'Financial information 1 Pt1'!$E$5,"Profit Model label","Fixed Expense")+'Financial information 1 Pt1'!$B$37 -> 10150 | ... M16: =GETPIVOTDATA("Expense/revenue",'Financial information 1 Pt1'!$E$5,"Profit Model label","Fixed Expense")+'Financial information 1 Pt1'!$B$37 -> 10150 | N16: =SUM(B16:M16) -> 121800
A18: Variable Expenses
A19: Coffee Variable expense | B19: =$E$2*GETPIVOTDATA("Expense/revenue",'Financial information 1 Pt1'!$E$5,"Profit Model label","Variable Expense: Coffee") -> 2640 | C19: =$E$2*GETPIVOTDATA("Expense/revenue",'Financial information 1 Pt1'!$E$5,"Profit Model label","Variable Expense: Coffee") -> 2640 | D19: =$E$2*GETPIVOTDATA("Expense/revenue",'Financial information 1 Pt1'!$E$5,"Profit Model label","Variable Expense: Coffee") -> 2640 | E19: =$E$2*GETPIVOTDATA("Expense/revenue",'Financial information 1 Pt1'!$E$5,"Profit Model label","Variable Expense: Coffee") -> 2640 | F19: =$E$2*GETPIVOTDATA("Expense/revenue",'Financial information 1 Pt1'!$E$5,"Profit Model label","Variable Expense: Coffee") -> 2640 | G19: =$E$2*GETPIVOTDATA("Expense/revenue",'Financial information 1 Pt1'!$E$5,"Profit Model label","Variable Expense: Coffee") -> 2640 | H19: =$E$2*GETPIVOTDATA("Expense/revenue",'Financial information 1 Pt1'!$E$5,"Profit Model label","Variable Expense: Coffee") -> 2640 | I19: =$E$2*GETPIVOTDATA("Expense/revenue",'Financial information 1 Pt1'!$E$5,"Profit Model label","Variable Expense: Coffee") -> 2640 | ... M19: =$E$2*GETPIVOTDATA("Expense/revenue",'Financial information 1 Pt1'!$E$5,"Profit Model label","Variable Expense: Coffee") -> 2640 | N19: =SUM(B19:M19) -> 31680
A20: Donut Variable expense | B20: =$E$2*GETPIVOTDATA("Expense/revenue",'Financial information 1 Pt1'!$E$5,"Profit Model label","Variable Expense: Donut") -> 3168 | C20: =$E$2*GETPIVOTDATA("Expense/revenue",'Financial information 1 Pt1'!$E$5,"Profit Model label","Variable Expense: Donut") -> 3168 | D20: =$E$2*GETPIVOTDATA("Expense/revenue",'Financial information 1 Pt1'!$E$5,"Profit Model label","Variable Expense: Donut") -> 3168 | E20: =$E$2*GETPIVOTDATA("Expense/revenue",'Financial information 1 Pt1'!$E$5,"Profit Model label","Variable Expense: Donut") -> 3168 | F20: =$E$2*GETPIVOTDATA("Expense/revenue",'Financial information 1 Pt1'!$E$5,"Profit Model label","Variable Expense: Donut") -> 3168 | G20: =$E$2*GETPIVOTDATA("Expense/revenue",'Financial information 1 Pt1'!$E$5,"Profit Model label","Variable Expense: Donut") -> 3168 | H20: =$E$2*GETPIVOTDATA("Expense/revenue",'Financial information 1 Pt1'!$E$5,"Profit Model label","Variable Expense: Donut") -> 3168 | I20: =$E$2*GETPIVOTDATA("Expense/revenue",'Financial information 1 Pt1'!$E$5,"Profit Model label","Variable Expense: Donut") -> 3168 | ... M20: =$E$2*GETPIVOTDATA("Expense/revenue",'Financial information 1 Pt1'!$E$5,"Profit Model label","Variable Expense: Donut") -> 3168 | N20: =SUM(B20:M20) -> 38016
A21: Total Variable Expenses | B21: =SUM(B19:B20) -> 5808 | C21: =SUM(C19:C20) -> 5808 | D21: =SUM(D19:D20) -> 5808 | E21: =SUM(E19:E20) -> 5808 | F21: =SUM(F19:F20) -> 5808 | G21: =SUM(G19:G20) -> 5808 | H21: =SUM(H19:H20) -> 5808 | I21: =SUM(I19:I20) -> 5808 | ... M21: =SUM(M19:M20) -> 5808 | N21: =SUM(B21:M21) -> 69696
A22: Expenses: due to lost sales | B22: =B8*$F$2 -> 0 | C22: =C8*$F$2 -> 0 | D22: =D8*$F$2 -> 0 | E22: =E8*$F$2 -> 0 | F22: =F8*$F$2 -> 445.25744 | G22: =G8*$F$2 -> 0 | H22: =H8*$F$2 -> 0 | I22: =I8*$F$2 -> 0 | ... M22: =M8*$F$2 -> 7689.4628 | N22: =SUM(B22:M22) -> 11770.08
A23: Total Expenses | B23: =B16+B21+B22 -> 15958 | C23: =C16+C21+C22 -> 15958 | D23: =D16+D21+D22 -> 15958 | E23: =E16+E21+E22 -> 15958 | F23: =F16+F21+F22 -> 16403.257 | G23: =G16+G21+G22 -> 15958 | H23: =H16+H21+H22 -> 15958 | I23: =I16+I21+I22 -> 15958 | ... M23: =M16+M21+M22 -> 23647.463 | N23: =SUM(B23:M23) -> 203266.08
A25: Profit Donuts and Coffee | B25: =B13-B23 -> 5705.3522 | C25: =C13-C23 -> 7987.4656 | D25: =D13-D23 -> 7279.6392 | E25: =E13-E23 -> 11966.327 | F25: =F13-F23 -> 12583.943 | G25: =G13-G23 -> 12198.238 | H25: =H13-H23 -> 6943.9267 | I25: =I13-I23 -> 10417.268 | ... M25: =M13-M23 -> 5339.7372 | N25: =SUM(B25:M25) -> 114133.09
B27: You should be able to copy from average to high and low and then just make some modifications
A28: HIGH DEMAND
A29: Month | B29: =B4 -> 44927 | C29: =C4 -> 44958 | D29: =D4 -> 44986 | E29: =E4 -> 45017 | F29: =F4 -> 45047 | G29: =G4 -> 45078 | H29: =H4 -> 45108 | I29: =I4 -> 45139 | ... M29: =M4 -> 45261 | N29: Yearly Total
A30: Demand | B30: =B5*(1+'Financial information 1 Pt1'!$B$34) -> 4334.2664 | C30: =C5*(1+'Financial information 1 Pt1'!$B$34) -> 4990.9123 | D30: =D5*(1+'Financial information 1 Pt1'!$B$34) -> 4787.2452 | E30: =E5*(1+'Financial information 1 Pt1'!$B$34) -> 6135.7734 | F30: =F5*(1+'Financial information 1 Pt1'!$B$34) -> 6622.6714 | G30: =G5*(1+'Financial information 1 Pt1'!$B$34) -> 6202.5024 | H30: =H5*(1+'Financial information 1 Pt1'!$B$34) -> 4690.6487 | I30: =I5*(1+'Financial information 1 Pt1'!$B$34) -> 5690.0536 | ... M30: =M5*(1+'Financial information 1 Pt1'!$B$34) -> 9568.6482 | N30: =SUM(B30:M30) -> 73324.939
A31: satisfied demand | B31: =MIN(B30,$E$2) -> 4334.2664 | C31: =MIN(C30,$E$2) -> 4990.9123 | D31: =MIN(D30,$E$2) -> 4787.2452 | E31: =MIN(E30,$E$2) -> 5280 | F31: =MIN(F30,$E$2) -> 5280 | G31: =MIN(G30,$E$2) -> 5280 | H31: =MIN(H30,$E$2) -> 4690.6487 | I31: =MIN(I30,$E$2) -> 5280 | ... M31: =MIN(M30,$E$2) -> 5280 | N31: =SUM(B31:M31) -> 61043.073
A32: Extra donuts(over) | B32: =IF(B30<$E$2,$E$2-B30,0) -> 945.73357 | C32: =IF(C30<$E$2,$E$2-C30,0) -> 289.08774 | D32: =IF(D30<$E$2,$E$2-D30,0) -> 492.75476 | E32: =IF(E30<$E$2,$E$2-E30,0) -> 0 | F32: =IF(F30<$E$2,$E$2-F30,0) -> 0 | G32: =IF(G30<$E$2,$E$2-G30,0) -> 0 | H32: =IF(H30<$E$2,$E$2-H30,0) -> 589.35129 | I32: =IF(I30<$E$2,$E$2-I30,0) -> 0 | ... M32: =IF(M30<$E$2,$E$2-M30,0) -> 0 | N32: =SUM(B32:M32) -> 2316.9274
A33: Unsatisfied customers (short) | B33: =IF(B30>$E$2,B30-$E$2,0) -> 0 | C33: =IF(C30>$E$2,C30-$E$2,0) -> 0 | D33: =IF(D30>$E$2,D30-$E$2,0) -> 0 | E33: =IF(E30>$E$2,E30-$E$2,0) -> 855.77341 | F33: =IF(F30>$E$2,F30-$E$2,0) -> 1342.6714 | G33: =IF(G30>$E$2,G30-$E$2,0) -> 922.50236 | H33: =IF(H30>$E$2,H30-$E$2,0) -> 0 | I33: =IF(I30>$E$2,I30-$E$2,0) -> 410.05356 | ... M33: =IF(M30>$E$2,M30-$E$2,0) -> 4288.6482 | N33: =SUM(B33:M33) -> 12281.866
A34: Revenue
A35: coffee | B35: =B31*'Financial information 1 Pt1'!$C$7 -> 12959.457 | C35: =C31*'Financial information 1 Pt1'!$C$7 -> 14922.828 | D35: =D31*'Financial information 1 Pt1'!$C$7 -> 14313.863 | E35: =E31*'Financial information 1 Pt1'!$C$7 -> 15787.2 | F35: =F31*'Financial information 1 Pt1'!$C$7 -> 15787.2 | G35: =G31*'Financial information 1 Pt1'!$C$7 -> 15787.2 | H35: =H31*'Financial information 1 Pt1'!$C$7 -> 14025.04 | I35: =I31*'Financial information 1 Pt1'!$C$7 -> 15787.2 | ... M35: =M31*'Financial information 1 Pt1'!$C$7 -> 15787.2 | N35: =SUM(B35:M35) -> 182518.79
A36: donut | B36: =B31*'Financial information 1 Pt1'!$C$8 -> 10835.666 | C36: =C31*'Financial information 1 Pt1'!$C$8 -> 12477.281 | D36: =D31*'Financial information 1 Pt1'!$C$8 -> 11968.113 | E36: =E31*'Financial information 1 Pt1'!$C$8 -> 13200 | F36: =F31*'Financial information 1 Pt1'!$C$8 -> 13200 | G36: =G31*'Financial information 1 Pt1'!$C$8 -> 13200 | H36: =H31*'Financial information 1 Pt1'!$C$8 -> 11726.622 | I36: =I31*'Financial information 1 Pt1'!$C$8 -> 13200 | ... M36: =M31*'Financial information 1 Pt1'!$C$8 -> 13200 | N36: =SUM(B36:M36) -> 152607.68
A37: Revenue from day old sales | B37: =B32*$G$2 -> 1182.167 | C37: =C32*$G$2 -> 361.35967 | D37: =D32*$G$2 -> 615.94345 | E37: =E32*$G$2 -> 0 | F37: =F32*$G$2 -> 0 | G37: =G32*$G$2 -> 0 | H37: =H32*$G$2 -> 736.68911 | I37: =I32*$G$2 -> 0 | ... M37: =M32*$G$2 -> 0 | N37: =SUM(B37:M37) -> 2896.1592
A38: Total Revenue | B38: =SUM(B35:B37) -> 24977.29 | C38: =SUM(C35:C37) -> 27761.468 | D38: =SUM(D35:D37) -> 26897.92 | E38: =SUM(E35:E37) -> 28987.2 | F38: =SUM(F35:F37) -> 28987.2 | G38: =SUM(G35:G37) -> 28987.2 | H38: =SUM(H35:H37) -> 26488.351 | I38: =SUM(I35:I37) -> 28987.2 | ... M38: =SUM(M35:M37) -> 28987.2 | N38: =SUM(B38:M38) -> 338022.63
A39: Expenses
A40: Fixed Expenses | B40: =GETPIVOTDATA("Expense/revenue",'Financial information 1 Pt1'!$E$5,"Profit Model label","Fixed Expense")+'Financial information 1 Pt1'!$B$37 -> 10150 | C40: =GETPIVOTDATA("Expense/revenue",'Financial information 1 Pt1'!$E$5,"Profit Model label","Fixed Expense")+'Financial information 1 Pt1'!$B$37 -> 10150 | D40: =GETPIVOTDATA("Expense/revenue",'Financial information 1 Pt1'!$E$5,"Profit Model label","Fixed Expense")+'Financial information 1 Pt1'!$B$37 -> 10150 | E40: =GETPIVOTDATA("Expense/revenue",'Financial information 1 Pt1'!$E$5,"Profit Model label","Fixed Expense")+'Financial information 1 Pt1'!$B$37 -> 10150 | F40: =GETPIVOTDATA("Expense/revenue",'Financial information 1 Pt1'!$E$5,"Profit Model label","Fixed Expense")+'Financial information 1 Pt1'!$B$37 -> 10150 | G40: =GETPIVOTDATA("Expense/revenue",'Financial information 1 Pt1'!$E$5,"Profit Model label","Fixed Expense")+'Financial information 1 Pt1'!$B$37 -> 10150 | H40: =GETPIVOTDATA("Expense/revenue",'Financial information 1 Pt1'!$E$5,"Profit Model label","Fixed Expense")+'Financial information 1 Pt1'!$B$37 -> 10150 | I40: =GETPIVOTDATA("Expense/revenue",'Financial information 1 Pt1'!$E$5,"Profit Model label","Fixed Expense")+'Financial information 1 Pt1'!$B$37 -> 10150 | ... M40: =GETPIVOTDATA("Expense/revenue",'Financial information 1 Pt1'!$E$5,"Profit Model label","Fixed Expense")+'Financial information 1 Pt1'!$B$37 -> 10150 | N40: =SUM(B40:M40) -> 121800
A41: Total Fixed Expense | B41: =GETPIVOTDATA("Expense/revenue",'Financial information 1 Pt1'!$E$5,"Profit Model label","Fixed Expense")+'Financial information 1 Pt1'!$B$37 -> 10150 | C41: =GETPIVOTDATA("Expense/revenue",'Financial information 1 Pt1'!$E$5,"Profit Model label","Fixed Expense")+'Financial information 1 Pt1'!$B$37 -> 10150 | D41: =GETPIVOTDATA("Expense/revenue",'Financial information 1 Pt1'!$E$5,"Profit Model label","Fixed Expense")+'Financial information 1 Pt1'!$B$37 -> 10150 | E41: =GETPIVOTDATA("Expense/revenue",'Financial information 1 Pt1'!$E$5,"Profit Model label","Fixed Expense")+'Financial information 1 Pt1'!$B$37 -> 10150 | F41: =GETPIVOTDATA("Expense/revenue",'Financial information 1 Pt1'!$E$5,"Profit Model label","Fixed Expense")+'Financial information 1 Pt1'!$B$37 -> 10150 | G41: =GETPIVOTDATA("Expense/revenue",'Financial information 1 Pt1'!$E$5,"Profit Model label","Fixed Expense")+'Financial information 1 Pt1'!$B$37 -> 10150 | H41: =GETPIVOTDATA("Expense/revenue",'Financial information 1 Pt1'!$E$5,"Profit Model label","Fixed Expense")+'Financial information 1 Pt1'!$B$37 -> 10150 | I41: =GETPIVOTDATA("Expense/revenue",'Financial information 1 Pt1'!$E$5,"Profit Model label","Fixed Expense")+'Financial information 1 Pt1'!$B$37 -> 10150 | ... M41: =GETPIVOTDATA("Expense/revenue",'Financial information 1 Pt1'!$E$5,"Profit Model label","Fixed Expense")+'Financial information 1 Pt1'!$B$37 -> 10150 | N41: =SUM(B41:M41) -> 121800
A43: Variable Expenses
A44: Coffee Variable expense | B44: =$E$2*GETPIVOTDATA("Expense/revenue",'Financial information 1 Pt1'!$E$5,"Profit Model label","Variable Expense: Coffee") -> 2640 | C44: =$E$2*GETPIVOTDATA("Expense/revenue",'Financial information 1 Pt1'!$E$5,"Profit Model label","Variable Expense: Coffee") -> 2640 | D44: =$E$2*GETPIVOTDATA("Expense/revenue",'Financial information 1 Pt1'!$E$5,"Profit Model label","Variable Expense: Coffee") -> 2640 | E44: =$E$2*GETPIVOTDATA("Expense/revenue",'Financial information 1 Pt1'!$E$5,"Profit Model label","Variable Expense: Coffee") -> 2640 | F44: =$E$2*GETPIVOTDATA("Expense/revenue",'Financial information 1 Pt1'!$E$5,"Profit Model label","Variable Expense: Coffee") -> 2640 | G44: =$E$2*GETPIVOTDATA("Expense/revenue",'Financial information 1 Pt1'!$E$5,"Profit Model label","Variable Expense: Coffee") -> 2640 | H44: =$E$2*GETPIVOTDATA("Expense/revenue",'Financial information 1 Pt1'!$E$5,"Profit Model label","Variable Expense: Coffee") -> 2640 | I44: =$E$2*GETPIVOTDATA("Expense/revenue",'Financial information 1 Pt1'!$E$5,"Profit Model label","Variable Expense: Coffee") -> 2640 | ... M44: =$E$2*GETPIVOTDATA("Expense/revenue",'Financial information 1 Pt1'!$E$5,"Profit Model label","Variable Expense: Coffee") -> 2640 | N44: =SUM(B44:M44) -> 31680
A45: Donut Variable expense | B45: =$E$2*GETPIVOTDATA("Expense/revenue",'Financial information 1 Pt1'!$E$5,"Profit Model label","Variable Expense: Donut") -> 3168 | C45: =$E$2*GETPIVOTDATA("Expense/revenue",'Financial information 1 Pt1'!$E$5,"Profit Model label","Variable Expense: Donut") -> 3168 | D45: =$E$2*GETPIVOTDATA("Expense/revenue",'Financial information 1 Pt1'!$E$5,"Profit Model label","Variable Expense: Donut") -> 3168 | E45: =$E$2*GETPIVOTDATA("Expense/revenue",'Financial information 1 Pt1'!$E$5,"Profit Model label","Variable Expense: Donut") -> 3168 | F45: =$E$2*GETPIVOTDATA("Expense/revenue",'Financial information 1 Pt1'!$E$5,"Profit Model label","Variable Expense: Donut") -> 3168 | G45: =$E$2*GETPIVOTDATA("Expense/revenue",'Financial information 1 Pt1'!$E$5,"Profit Model label","Variable Expense: Donut") -> 3168 | H45: =$E$2*GETPIVOTDATA("Expense/revenue",'Financial information 1 Pt1'!$E$5,"Profit Model label","Variable Expense: Donut") -> 3168 | I45: =$E$2*GETPIVOTDATA("Expense/revenue",'Financial information 1 Pt1'!$E$5,"Profit Model label","Variable Expense: Donut") -> 3168 | ... M45: =$E$2*GETPIVOTDATA("Expense/revenue",'Financial information 1 Pt1'!$E$5,"Profit Model label","Variable Expense: Donut") -> 3168 | N45: =SUM(B45:M45) -> 38016
A46: Total Variable Expenses | B46: =SUM(B44:B45) -> 5808 | C46: =SUM(C44:C45) -> 5808 | D46: =SUM(D44:D45) -> 5808 | E46: =SUM(E44:E45) -> 5808 | F46: =SUM(F44:F45) -> 5808 | G46: =SUM(G44:G45) -> 5808 | H46: =SUM(H44:H45) -> 5808 | I46: =SUM(I44:I45) -> 5808 | ... M46: =SUM(M44:M45) -> 5808 | N46: =SUM(B46:M46) -> 69696
A47: Expenses: due to lost sales | B47: =B33*$F$2 -> 0 | C47: =C33*$F$2 -> 0 | D47: =D33*$F$2 -> 0 | E47: =E33*$F$2 -> 2567.3202 | F47: =F33*$F$2 -> 4028.0141 | G47: =G33*$F$2 -> 2767.5071 | H47: =H33*$F$2 -> 0 | I47: =I33*$F$2 -> 1230.1607 | ... M47: =M33*$F$2 -> 12865.945 | N47: =SUM(B47:M47) -> 36845.599
A48: Total Expenses | B48: =B41+B46+B47 -> 15958 | C48: =C41+C46+C47 -> 15958 | D48: =D41+D46+D47 -> 15958 | E48: =E41+E46+E47 -> 18525.32 | F48: =F41+F46+F47 -> 19986.014 | G48: =G41+G46+G47 -> 18725.507 | H48: =H41+H46+H47 -> 15958 | I48: =I41+I46+I47 -> 17188.161 | ... M48: =M41+M46+M47 -> 28823.945 | N48: =SUM(B48:M48) -> 228341.6
A50: Profit Donuts and Coffee | B50: =B38-B48 -> 9019.2897 | C50: =C38-C48 -> 11803.468 | D50: =D38-D48 -> 10939.92 | E50: =E38-E48 -> 10461.88 | F50: =F38-F48 -> 9001.1859 | G50: =G38-G48 -> 10261.693 | H50: =H38-H48 -> 10530.351 | I50: =I38-I48 -> 11799.039 | ... M50: =M38-M48 -> 163.25544 | N50: =SUM(B50:M50) -> 109681.03
A53: LOW DEMAND
A54: Month | B54: =B29 -> 44927 | C54: =C29 -> 44958 | D54: =D29 -> 44986 | E54: =E29 -> 45017 | F54: =F29 -> 45047 | G54: =G29 -> 45078 | H54: =H29 -> 45108 | I54: =I29 -> 45139 | ... M54: =M29 -> 45261 | N54: Yearly Total
A55: Demand | B55: =B5*(1-'Financial information 1 Pt1'!$B$35) -> 2628.9813 | C55: =C5*(1-'Financial information 1 Pt1'!$B$35) -> 3027.2747 | D55: =D5*(1-'Financial information 1 Pt1'!$B$35) -> 2903.7389 | E55: =E5*(1-'Financial information 1 Pt1'!$B$35) -> 3721.6986 | F55: =F5*(1-'Financial information 1 Pt1'!$B$35) -> 4017.0302 | G55: =G5*(1-'Financial information 1 Pt1'!$B$35) -> 3762.1736 | H55: =H5*(1-'Financial information 1 Pt1'!$B$35) -> 2845.1476 | I55: =I5*(1-'Financial information 1 Pt1'!$B$35) -> 3451.344 | ... M55: =M5*(1-'Financial information 1 Pt1'!$B$35) -> 5803.9341 | N55: =SUM(B55:M55) -> 44475.783
A56: satisfied demand | B56: =MIN(B55,$E$2) -> 2628.9813 | C56: =MIN(C55,$E$2) -> 3027.2747 | D56: =MIN(D55,$E$2) -> 2903.7389 | E56: =MIN(E55,$E$2) -> 3721.6986 | F56: =MIN(F55,$E$2) -> 4017.0302 | G56: =MIN(G55,$E$2) -> 3762.1736 | H56: =MIN(H55,$E$2) -> 2845.1476 | I56: =MIN(I55,$E$2) -> 3451.344 | ... M56: =MIN(M55,$E$2) -> 5280 | N56: =SUM(B56:M56) -> 43951.849
A57: Extra donuts(over) | B57: =IF(B55<$E$2,$E$2-B55,0) -> 2651.0187 | C57: =IF(C55<$E$2,$E$2-C55,0) -> 2252.7253 | D57: =IF(D55<$E$2,$E$2-D55,0) -> 2376.2611 | E57: =IF(E55<$E$2,$E$2-E55,0) -> 1558.3014 | F57: =IF(F55<$E$2,$E$2-F55,0) -> 1262.9698 | G57: =IF(G55<$E$2,$E$2-G55,0) -> 1517.8264 | H57: =IF(H55<$E$2,$E$2-H55,0) -> 2434.8524 | I57: =IF(I55<$E$2,$E$2-I55,0) -> 1828.656 | ... M57: =IF(M55<$E$2,$E$2-M55,0) -> 0 | N57: =SUM(B57:M57) -> 19408.151
A58: Unsatisfied customers (short) | B58: =IF(B55>$E$2,B55-$E$2,0) -> 0 | C58: =IF(C55>$E$2,C55-$E$2,0) -> 0 | D58: =IF(D55>$E$2,D55-$E$2,0) -> 0 | E58: =IF(E55>$E$2,E55-$E$2,0) -> 0 | F58: =IF(F55>$E$2,F55-$E$2,0) -> 0 | G58: =IF(G55>$E$2,G55-$E$2,0) -> 0 | H58: =IF(H55>$E$2,H55-$E$2,0) -> 0 | I58: =IF(I55>$E$2,I55-$E$2,0) -> 0 | ... M58: =IF(M55>$E$2,M55-$E$2,0) -> 523.93415 | N58: =SUM(B58:M58) -> 523.93415
A59: Revenue
A60: coffee | B60: =B56*'Financial information 1 Pt1'!$C$7 -> 7860.654 | C60: =C56*'Financial information 1 Pt1'!$C$7 -> 9051.5512 | D60: =D56*'Financial information 1 Pt1'!$C$7 -> 8682.1794 | E60: =E56*'Financial information 1 Pt1'!$C$7 -> 11127.879 | F60: =F56*'Financial information 1 Pt1'!$C$7 -> 12010.92 | G60: =G56*'Financial information 1 Pt1'!$C$7 -> 11248.899 | H60: =H56*'Financial information 1 Pt1'!$C$7 -> 8506.9913 | I60: =I56*'Financial information 1 Pt1'!$C$7 -> 10319.518 | ... M60: =M56*'Financial information 1 Pt1'!$C$7 -> 15787.2 | N60: =SUM(B60:M60) -> 131416.03
A61: donut | B61: =B56*'Financial information 1 Pt1'!$C$8 -> 6572.4532 | C61: =C56*'Financial information 1 Pt1'!$C$8 -> 7568.1866 | D61: =D56*'Financial information 1 Pt1'!$C$8 -> 7259.3473 | E61: =E56*'Financial information 1 Pt1'!$C$8 -> 9304.2466 | F61: =F56*'Financial information 1 Pt1'!$C$8 -> 10042.575 | G61: =G56*'Financial information 1 Pt1'!$C$8 -> 9405.4339 | H61: =H56*'Financial information 1 Pt1'!$C$8 -> 7112.8689 | I61: =I56*'Financial information 1 Pt1'!$C$8 -> 8628.3599 | ... M61: =M56*'Financial information 1 Pt1'!$C$8 -> 13200 | N61: =SUM(B61:M61) -> 109879.62
A62: Revenue from day old sales | B62: =B57*$G$2 -> 3313.7734 | C62: =C57*$G$2 -> 2815.9067 | D62: =D57*$G$2 -> 2970.3264 | E62: =E57*$G$2 -> 1947.8767 | F62: =F57*$G$2 -> 1578.7123 | G62: =G57*$G$2 -> 1897.283 | H62: =H57*$G$2 -> 3043.5655 | I62: =I57*$G$2 -> 2285.82 | ... M62: =M57*$G$2 -> 0 | N62: =SUM(B62:M62) -> 24260.189
A63: Total Revenue | B63: =SUM(B60:B62) -> 17746.881 | C63: =SUM(C60:C62) -> 19435.645 | D63: =SUM(D60:D62) -> 18911.853 | E63: =SUM(E60:E62) -> 22380.002 | F63: =SUM(F60:F62) -> 23632.208 | G63: =SUM(G60:G62) -> 22551.616 | H63: =SUM(H60:H62) -> 18663.426 | I63: =SUM(I60:I62) -> 21233.698 | ... M63: =SUM(M60:M62) -> 28987.2 | N63: =SUM(B63:M63) -> 265555.84
A64: Expenses
A65: Fixed Expenses | B65: =GETPIVOTDATA("Expense/revenue",'Financial information 1 Pt1'!$E$5,"Profit Model label","Fixed Expense")+'Financial information 1 Pt1'!$B$37 -> 10150 | C65: =GETPIVOTDATA("Expense/revenue",'Financial information 1 Pt1'!$E$5,"Profit Model label","Fixed Expense") -> 5800 | D65: =GETPIVOTDATA("Expense/revenue",'Financial information 1 Pt1'!$E$5,"Profit Model label","Fixed Expense") -> 5800 | E65: =GETPIVOTDATA("Expense/revenue",'Financial information 1 Pt1'!$E$5,"Profit Model label","Fixed Expense") -> 5800 | F65: =GETPIVOTDATA("Expense/revenue",'Financial information 1 Pt1'!$E$5,"Profit Model label","Fixed Expense") -> 5800 | G65: =GETPIVOTDATA("Expense/revenue",'Financial information 1 Pt1'!$E$5,"Profit Model label","Fixed Expense") -> 5800 | H65: =GETPIVOTDATA("Expense/revenue",'Financial information 1 Pt1'!$E$5,"Profit Model label","Fixed Expense") -> 5800 | I65: =GETPIVOTDATA("Expense/revenue",'Financial information 1 Pt1'!$E$5,"Profit Model label","Fixed Expense") -> 5800 | J65: =GETPIVOTDATA("Expense/revenue",'Financial information 1 Pt1'!$E$5,"Profit Model label","Fixed Expense") -> 5800 | ... M65: =GETPIVOTDATA("Expense/revenue",'Financial information 1 Pt1'!$E$5,"Profit Model label","Fixed Expense") -> 5800 | N65: =SUM(B65:M65) -> 73950
A66: Total Fixed Expense | B66: =GETPIVOTDATA("Expense/revenue",'Financial information 1 Pt1'!$E$5,"Profit Model label","Fixed Expense")+'Financial information 1 Pt1'!$B$37 -> 10150 | C66: =GETPIVOTDATA("Expense/revenue",'Financial information 1 Pt1'!$E$5,"Profit Model label","Fixed Expense") -> 5800 | D66: =GETPIVOTDATA("Expense/revenue",'Financial information 1 Pt1'!$E$5,"Profit Model label","Fixed Expense") -> 5800 | E66: =GETPIVOTDATA("Expense/revenue",'Financial information 1 Pt1'!$E$5,"Profit Model label","Fixed Expense") -> 5800 | F66: =GETPIVOTDATA("Expense/revenue",'Financial information 1 Pt1'!$E$5,"Profit Model label","Fixed Expense") -> 5800 | G66: =GETPIVOTDATA("Expense/revenue",'Financial information 1 Pt1'!$E$5,"Profit Model label","Fixed Expense") -> 5800 | H66: =GETPIVOTDATA("Expense/revenue",'Financial information 1 Pt1'!$E$5,"Profit Model label","Fixed Expense") -> 5800 | I66: =GETPIVOTDATA("Expense/revenue",'Financial information 1 Pt1'!$E$5,"Profit Model label","Fixed Expense") -> 5800 | J66: =GETPIVOTDATA("Expense/revenue",'Financial information 1 Pt1'!$E$5,"Profit Model label","Fixed Expense") -> 5800 | ... M66: =GETPIVOTDATA("Expense/revenue",'Financial information 1 Pt1'!$E$5,"Profit Model label","Fixed Expense") -> 5800 | N66: =SUM(B66:M66) -> 73950
A68: Variable Expenses
A69: Coffee Variable expense | B69: =$E$2*GETPIVOTDATA("Expense/revenue",'Financial information 1 Pt1'!$E$5,"Profit Model label","Variable Expense: Coffee") -> 2640 | C69: =$E$2*GETPIVOTDATA("Expense/revenue",'Financial information 1 Pt1'!$E$5,"Profit Model label","Variable Expense: Coffee") -> 2640 | D69: =$E$2*GETPIVOTDATA("Expense/revenue",'Financial information 1 Pt1'!$E$5,"Profit Model label","Variable Expense: Coffee") -> 2640 | E69: =$E$2*GETPIVOTDATA("Expense/revenue",'Financial information 1 Pt1'!$E$5,"Profit Model label","Variable Expense: Coffee") -> 2640 | F69: =$E$2*GETPIVOTDATA("Expense/revenue",'Financial information 1 Pt1'!$E$5,"Profit Model label","Variable Expense: Coffee") -> 2640 | G69: =$E$2*GETPIVOTDATA("Expense/revenue",'Financial information 1 Pt1'!$E$5,"Profit Model label","Variable Expense: Coffee") -> 2640 | H69: =$E$2*GETPIVOTDATA("Expense/revenue",'Financial information 1 Pt1'!$E$5,"Profit Model label","Variable Expense: Coffee") -> 2640 | I69: =$E$2*GETPIVOTDATA("Expense/revenue",'Financial information 1 Pt1'!$E$5,"Profit Model label","Variable Expense: Coffee") -> 2640 | ... M69: =$E$2*GETPIVOTDATA("Expense/revenue",'Financial information 1 Pt1'!$E$5,"Profit Model label","Variable Expense: Coffee") -> 2640 | N69: =SUM(B69:M69) -> 31680
A70: Donut Variable expense | B70: =$E$2*GETPIVOTDATA("Expense/revenue",'Financial information 1 Pt1'!$E$5,"Profit Model label","Variable Expense: Donut") -> 3168 | C70: =$E$2*GETPIVOTDATA("Expense/revenue",'Financial information 1 Pt1'!$E$5,"Profit Model label","Variable Expense: Donut") -> 3168 | D70: =$E$2*GETPIVOTDATA("Expense/revenue",'Financial information 1 Pt1'!$E$5,"Profit Model label","Variable Expense: Donut") -> 3168 | E70: =$E$2*GETPIVOTDATA("Expense/revenue",'Financial information 1 Pt1'!$E$5,"Profit Model label","Variable Expense: Donut") -> 3168 | F70: =$E$2*GETPIVOTDATA("Expense/revenue",'Financial information 1 Pt1'!$E$5,"Profit Model label","Variable Expense: Donut") -> 3168 | G70: =$E$2*GETPIVOTDATA("Expense/revenue",'Financial information 1 Pt1'!$E$5,"Profit Model label","Variable Expense: Donut") -> 3168 | H70: =$E$2*GETPIVOTDATA("Expense/revenue",'Financial information 1 Pt1'!$E$5,"Profit Model label","Variable Expense: Donut") -> 3168 | I70: =$E$2*GETPIVOTDATA("Expense/revenue",'Financial information 1 Pt1'!$E$5,"Profit Model label","Variable Expense: Donut") -> 3168 | ... M70: =$E$2*GETPIVOTDATA("Expense/revenue",'Financial information 1 Pt1'!$E$5,"Profit Model label","Variable Expense: Donut") -> 3168 | N70: =SUM(B70:M70) -> 38016
A71: Total Variable Expenses | B71: =SUM(B69:B70) -> 5808 | C71: =SUM(C69:C70) -> 5808 | D71: =SUM(D69:D70) -> 5808 | E71: =SUM(E69:E70) -> 5808 | F71: =SUM(F69:F70) -> 5808 | G71: =SUM(G69:G70) -> 5808 | H71: =SUM(H69:H70) -> 5808 | I71: =SUM(I69:I70) -> 5808 | ... M71: =SUM(M69:M70) -> 5808 | N71: =SUM(B71:M71) -> 69696
A72: Expenses: due to lost sales | B72: =B58*$F$2 -> 0 | C72: =C58*$F$2 -> 0 | D72: =D58*$F$2 -> 0 | E72: =E58*$F$2 -> 0 | F72: =F58*$F$2 -> 0 | G72: =G58*$F$2 -> 0 | H72: =H58*$F$2 -> 0 | I72: =I58*$F$2 -> 0 | ... M72: =M58*$F$2 -> 1571.8024 | N72: =SUM(B72:M72) -> 1571.8024
A73: Total Expenses | B73: =B66+B71+B72 -> 15958 | C73: =C66+C71+C72 -> 11608 | D73: =D66+D71+D72 -> 11608 | E73: =E66+E71+E72 -> 11608 | F73: =F66+F71+F72 -> 11608 | G73: =G66+G71+G72 -> 11608 | H73: =H66+H71+H72 -> 11608 | I73: =I66+I71+I72 -> 11608 | ... M73: =M66+M71+M72 -> 13179.802 | N73: =SUM(B73:M73) -> 145217.8
A75: Profit Donuts and Coffee | B75: =B63-B73 -> 1788.8806 | C75: =C63-C73 -> 7827.6445 | D75: =D63-D73 -> 7303.853 | E75: =E63-E73 -> 10772.002 | F75: =F63-F73 -> 12024.208 | G75: =G63-G73 -> 10943.616 | H75: =H63-H73 -> 7055.4257 | I75: =I63-I73 -> 9625.6984 | ... M75: =M63-M73 -> 15807.398 | N75: 72488.04

Sheet Current operations  Pt3 
A1: CURRENT OPERATIONS | B1: Reminder: Format Cells to show 2 decimal places | E1: Monthly Production | F1: Lost Sales | G1: Day old revenue | Z1: Fall 25
E2: ='Financial information 1 Pt1'!B31 -> 4000 | F2: ='Financial information 1 Pt1'!B32 -> 3 | G2: ='Financial information 1 Pt1'!B33 -> 1.25
A3: AVERAGE DEMAND
A4: Month | B4: 44927 | C4: 44958 | D4: 44986 | E4: 45017 | F4: 45047 | G4: 45078 | H4: 45108 | I4: 45139 | J4: 45170 | K4: 45200 | L4: 45231 | M4: 45261 | N4: Yearly Total
A5: Demand | B5: ='SI and regression Pt 2'!I38 -> 2912.0307 | C5: ='SI and regression Pt 2'!I39 -> 3353.2063 | D5: ='SI and regression Pt 2'!I40 -> 3216.3701 | E5: ='SI and regression Pt 2'!I41 -> 4122.3955 | F5: ='SI and regression Pt 2'!I42 -> 4449.5239 | G5: ='SI and regression Pt 2'!I43 -> 4167.2281 | H5: ='SI and regression Pt 2'!I44 -> 3151.4705 | I5: ='SI and regression Pt 2'!I45 -> 3822.9331 | J5: ='SI and regression Pt 2'!I46 -> 3991.2912 | K5: ='SI and regression Pt 2'!I47 -> 4542.9104 | L5: ='SI and regression Pt 2'!I48 -> 5106.0951 | M5: ='SI and regression Pt 2'!I49 -> 6428.815 | N5: =SUM(B5:M5) -> 49264.27
A6: satisfied demand | B6: =MIN(B5,$E$2) -> 2912.0307 | C6: =MIN(C5,$E$2) -> 3353.2063 | D6: =MIN(D5,$E$2) -> 3216.3701 | E6: =MIN(E5,$E$2) -> 4000 | F6: =MIN(F5,$E$2) -> 4000 | G6: =MIN(G5,$E$2) -> 4000 | H6: =MIN(H5,$E$2) -> 3151.4705 | I6: =MIN(I5,$E$2) -> 3822.9331 | ... M6: =MIN(M5,$E$2) -> 4000 | N6: =SUM(B6:M6) -> 44447.302
A7: Extra donuts(over) | B7: =IF(B5<$E$2,$E$2-B5,0) -> 1087.9693 | C7: =IF(C5<$E$2,$E$2-C5,0) -> 646.7937 | D7: =IF(D5<$E$2,$E$2-D5,0) -> 783.62991 | E7: =IF(E5<$E$2,$E$2-E5,0) -> 0 | F7: =IF(F5<$E$2,$E$2-F5,0) -> 0 | G7: =IF(G5<$E$2,$E$2-G5,0) -> 0 | H7: =IF(H5<$E$2,$E$2-H5,0) -> 848.52949 | I7: =IF(I5<$E$2,$E$2-I5,0) -> 177.06694 | ... M7: =IF(M5<$E$2,$E$2-M5,0) -> 0 | N7: =SUM(B7:M7) -> 3552.6982
A8: Unsatisfied customers (short) | B8: =IF(B5>$E$2,B5-$E$2,0) -> 0 | C8: =IF(C5>$E$2,C5-$E$2,0) -> 0 | D8: =IF(D5>$E$2,D5-$E$2,0) -> 0 | E8: =IF(E5>$E$2,E5-$E$2,0) -> 122.39547 | F8: =IF(F5>$E$2,F5-$E$2,0) -> 449.52389 | G8: =IF(G5>$E$2,G5-$E$2,0) -> 167.22814 | H8: =IF(H5>$E$2,H5-$E$2,0) -> 0 | I8: =IF(I5>$E$2,I5-$E$2,0) -> 0 | ... M8: =IF(M5>$E$2,M5-$E$2,0) -> 2428.815 | N8: =SUM(B8:M8) -> 4816.9679
A9: Revenue
A10: coffee | B10: =B6*'Financial information 1 Pt1'!$C$7 -> 8706.9717 | C10: =C6*'Financial information 1 Pt1'!$C$7 -> 10026.087 | D10: =D6*'Financial information 1 Pt1'!$C$7 -> 9616.9466 | E10: =E6*'Financial information 1 Pt1'!$C$7 -> 11960 | F10: =F6*'Financial information 1 Pt1'!$C$7 -> 11960 | G10: =G6*'Financial information 1 Pt1'!$C$7 -> 11960 | H10: =H6*'Financial information 1 Pt1'!$C$7 -> 9422.8968 | I10: =I6*'Financial information 1 Pt1'!$C$7 -> 11430.57 | ... M10: =M6*'Financial information 1 Pt1'!$C$7 -> 11960 | N10: =SUM(B10:M10) -> 132897.43
A11: donut | B11: =B6*'Financial information 1 Pt1'!$C$8 -> 7280.0766 | C11: =C6*'Financial information 1 Pt1'!$C$8 -> 8383.0158 | D11: =D6*'Financial information 1 Pt1'!$C$8 -> 8040.9252 | E11: =E6*'Financial information 1 Pt1'!$C$8 -> 10000 | F11: =F6*'Financial information 1 Pt1'!$C$8 -> 10000 | G11: =G6*'Financial information 1 Pt1'!$C$8 -> 10000 | H11: =H6*'Financial information 1 Pt1'!$C$8 -> 7878.6763 | I11: =I6*'Financial information 1 Pt1'!$C$8 -> 9557.3326 | ... M11: =M6*'Financial information 1 Pt1'!$C$8 -> 10000 | N11: =SUM(B11:M11) -> 111118.25
A12: Revenue from day old sales | B12: =B7*$G$2 -> 1359.9617 | C12: =C7*$G$2 -> 808.49212 | D12: =D7*$G$2 -> 979.53739 | E12: =E7*$G$2 -> 0 | F12: =F7*$G$2 -> 0 | G12: =G7*$G$2 -> 0 | H12: =H7*$G$2 -> 1060.6619 | I12: =I7*$G$2 -> 221.33368 | ... M12: =M7*$G$2 -> 0 | N12: =SUM(B12:M12) -> 4440.8727
A13: Total Revenue | B13: =SUM(B10:B12) -> 17347.01 | C13: =SUM(C10:C12) -> 19217.595 | D13: =SUM(D10:D12) -> 18637.409 | E13: =SUM(E10:E12) -> 21960 | F13: =SUM(F10:F12) -> 21960 | G13: =SUM(G10:G12) -> 21960 | H13: =SUM(H10:H12) -> 18362.235 | I13: =SUM(I10:I12) -> 21209.236 | ... N13: =SUM(N10:N12) -> 248456.56
A14: Expenses
A15: Fixed Expenses | B15: =GETPIVOTDATA("Expense/revenue",'Financial information 1 Pt1'!$E$5,"Profit Model label","Fixed Expense") -> 5800 | C15: =GETPIVOTDATA("Expense/revenue",'Financial information 1 Pt1'!$E$5,"Profit Model label","Fixed Expense") -> 5800 | D15: =GETPIVOTDATA("Expense/revenue",'Financial information 1 Pt1'!$E$5,"Profit Model label","Fixed Expense") -> 5800 | E15: =GETPIVOTDATA("Expense/revenue",'Financial information 1 Pt1'!$E$5,"Profit Model label","Fixed Expense") -> 5800 | F15: =GETPIVOTDATA("Expense/revenue",'Financial information 1 Pt1'!$E$5,"Profit Model label","Fixed Expense") -> 5800 | G15: =GETPIVOTDATA("Expense/revenue",'Financial information 1 Pt1'!$E$5,"Profit Model label","Fixed Expense") -> 5800 | H15: =GETPIVOTDATA("Expense/revenue",'Financial information 1 Pt1'!$E$5,"Profit Model label","Fixed Expense") -> 5800 | I15: =GETPIVOTDATA("Expense/revenue",'Financial information 1 Pt1'!$E$5,"Profit Model label","Fixed Expense") -> 5800 | ... M15: =GETPIVOTDATA("Expense/revenue",'Financial information 1 Pt1'!$E$5,"Profit Model label","Fixed Expense") -> 5800 | N15: =SUM(B15:M15) -> 69600
A16: Total Fixed Expense | B16: =GETPIVOTDATA("Expense/revenue",'Financial information 1 Pt1'!$E$5,"Profit Model label","Fixed Expense") -> 5800 | C16: =GETPIVOTDATA("Expense/revenue",'Financial information 1 Pt1'!$E$5,"Profit Model label","Fixed Expense") -> 5800 | D16: =GETPIVOTDATA("Expense/revenue",'Financial information 1 Pt1'!$E$5,"Profit Model label","Fixed Expense") -> 5800 | E16: =GETPIVOTDATA("Expense/revenue",'Financial information 1 Pt1'!$E$5,"Profit Model label","Fixed Expense") -> 5800 | F16: =GETPIVOTDATA("Expense/revenue",'Financial information 1 Pt1'!$E$5,"Profit Model label","Fixed Expense") -> 5800 | G16: =GETPIVOTDATA("Expense/revenue",'Financial information 1 Pt1'!$E$5,"Profit Model label","Fixed Expense") -> 5800 | H16: =GETPIVOTDATA("Expense/revenue",'Financial information 1 Pt1'!$E$5,"Profit Model label","Fixed Expense") -> 5800 | I16: =GETPIVOTDATA("Expense/revenue",'Financial information 1 Pt1'!$E$5,"Profit Model label","Fixed Expense") -> 5800 | ... M16: =GETPIVOTDATA("Expense/revenue",'Financial information 1 Pt1'!$E$5,"Profit Model label","Fixed Expense") -> 5800 | N16: =SUM(B16:M16) -> 69600
A18: Variable Expenses
A19: Coffee Variable expense | B19: =$E$2*GETPIVOTDATA("Expense/revenue",'Financial information 1 Pt1'!$E$5,"Profit Model label","Variable Expense: Coffee") -> 2000 | C19: =$E$2*GETPIVOTDATA("Expense/revenue",'Financial information 1 Pt1'!$E$5,"Profit Model label","Variable Expense: Coffee") -> 2000 | D19: =$E$2*GETPIVOTDATA("Expense/revenue",'Financial information 1 Pt1'!$E$5,"Profit Model label","Variable Expense: Coffee") -> 2000 | E19: =$E$2*GETPIVOTDATA("Expense/revenue",'Financial information 1 Pt1'!$E$5,"Profit Model label","Variable Expense: Coffee") -> 2000 | F19: =$E$2*GETPIVOTDATA("Expense/revenue",'Financial information 1 Pt1'!$E$5,"Profit Model label","Variable Expense: Coffee") -> 2000 | G19: =$E$2*GETPIVOTDATA("Expense/revenue",'Financial information 1 Pt1'!$E$5,"Profit Model label","Variable Expense: Coffee") -> 2000 | H19: =$E$2*GETPIVOTDATA("Expense/revenue",'Financial information 1 Pt1'!$E$5,"Profit Model label","Variable Expense: Coffee") -> 2000 | I19: =$E$2*GETPIVOTDATA("Expense/revenue",'Financial information 1 Pt1'!$E$5,"Profit Model label","Variable Expense: Coffee") -> 2000 | ... M19: =$E$2*GETPIVOTDATA("Expense/revenue",'Financial information 1 Pt1'!$E$5,"Profit Model label","Variable Expense: Coffee") -> 2000 | N19: =SUM(B19:M19) -> 24000
A20: Donut Variable expense | B20: =$E$2*GETPIVOTDATA("Expense/revenue",'Financial information 1 Pt1'!$E$5,"Profit Model label","Variable Expense: Donut") -> 2400 | C20: =$E$2*GETPIVOTDATA("Expense/revenue",'Financial information 1 Pt1'!$E$5,"Profit Model label","Variable Expense: Donut") -> 2400 | D20: =$E$2*GETPIVOTDATA("Expense/revenue",'Financial information 1 Pt1'!$E$5,"Profit Model label","Variable Expense: Donut") -> 2400 | E20: =$E$2*GETPIVOTDATA("Expense/revenue",'Financial information 1 Pt1'!$E$5,"Profit Model label","Variable Expense: Donut") -> 2400 | F20: =$E$2*GETPIVOTDATA("Expense/revenue",'Financial information 1 Pt1'!$E$5,"Profit Model label","Variable Expense: Donut") -> 2400 | G20: =$E$2*GETPIVOTDATA("Expense/revenue",'Financial information 1 Pt1'!$E$5,"Profit Model label","Variable Expense: Donut") -> 2400 | H20: =$E$2*GETPIVOTDATA("Expense/revenue",'Financial information 1 Pt1'!$E$5,"Profit Model label","Variable Expense: Donut") -> 2400 | I20: =$E$2*GETPIVOTDATA("Expense/revenue",'Financial information 1 Pt1'!$E$5,"Profit Model label","Variable Expense: Donut") -> 2400 | ... M20: =$E$2*GETPIVOTDATA("Expense/revenue",'Financial information 1 Pt1'!$E$5,"Profit Model label","Variable Expense: Donut") -> 2400
A21: Total Variable Expenses | B21: =SUM(B19:B20) -> 4400 | C21: =SUM(C19:C20) -> 4400 | D21: =SUM(D19:D20) -> 4400 | E21: =SUM(E19:E20) -> 4400 | F21: =SUM(F19:F20) -> 4400 | G21: =SUM(G19:G20) -> 4400 | H21: =SUM(H19:H20) -> 4400 | I21: =SUM(I19:I20) -> 4400 | ... M21: =SUM(M19:M20) -> 4400 | N21: =SUM(B21:M21) -> 52800
A22: Expenses: due to lost sales | B22: =B8*$F$2 -> 0 | C22: =C8*$F$2 -> 0 | D22: =D8*$F$2 -> 0 | E22: =E8*$F$2 -> 367.1864 | F22: =F8*$F$2 -> 1348.5717 | G22: =G8*$F$2 -> 501.68441 | H22: =H8*$F$2 -> 0 | I22: =I8*$F$2 -> 0 | ... M22: =M8*$F$2 -> 7286.4449 | N22: =SUM(B22:M22) -> 14450.904
A23: Total Expenses | B23: =B16+B21+B22 -> 10200 | C23: =C16+C21+C22 -> 10200 | D23: =D16+D21+D22 -> 10200 | E23: =E16+E21+E22 -> 10567.186 | F23: =F16+F21+F22 -> 11548.572 | G23: =G16+G21+G22 -> 10701.684 | H23: =H16+H21+H22 -> 10200 | I23: =I16+I21+I22 -> 10200 | ... M23: =M16+M21+M22 -> 17486.445 | N23: =SUM(B23:M23) -> 136850.9
A25: Profit Donuts and Coffee | B25: =B13-B23 -> 7147.01 | C25: =C13-C23 -> 9017.5947 | D25: =D13-D23 -> 8437.4092 | E25: =E13-E23 -> 11392.814 | F25: =F13-F23 -> 10411.428 | G25: =G13-G23 -> 11258.316 | H25: =H13-H23 -> 8162.235 | I25: =I13-I23 -> 11009.236 | ... M25: =M13-M23 -> 4473.5551 | N25: =SUM(B25:M25) -> 111605.66
B27: You should be able to copy from average to high and low and then just make some modifications
A28: HIGH DEMAND
A29: Month | B29: =B4 -> 44927 | C29: =C4 -> 44958 | D29: =D4 -> 44986 | E29: =E4 -> 45017 | F29: =F4 -> 45047 | G29: =G4 -> 45078 | H29: =H4 -> 45108 | I29: =I4 -> 45139 | ... M29: =M4 -> 45261 | N29: Yearly Total
A30: Demand | B30: =B5*(1+'Financial information 1 Pt1'!$B$34) -> 3552.6774 | C30: =C5*(1+'Financial information 1 Pt1'!$B$34) -> 4090.9117 | D30: =D5*(1+'Financial information 1 Pt1'!$B$34) -> 3923.9715 | E30: =E5*(1+'Financial information 1 Pt1'!$B$34) -> 5029.3225 | F30: =F5*(1+'Financial information 1 Pt1'!$B$34) -> 5428.4191 | G30: =G5*(1+'Financial information 1 Pt1'!$B$34) -> 5084.0183 | H30: =H5*(1+'Financial information 1 Pt1'!$B$34) -> 3844.794 | I30: =I5*(1+'Financial information 1 Pt1'!$B$34) -> 4663.9783 | ... M30: =M5*(1+'Financial information 1 Pt1'!$B$34) -> 7843.1543 | N30: =SUM(B30:M30) -> 60102.409
A31: satisfied demand | B31: =MIN(B30,$E$2) -> 3552.6774 | C31: =MIN(C30,$E$2) -> 4000 | D31: =MIN(D30,$E$2) -> 3923.9715 | E31: =MIN(E30,$E$2) -> 4000 | F31: =MIN(F30,$E$2) -> 4000 | G31: =MIN(G30,$E$2) -> 4000 | H31: =MIN(H30,$E$2) -> 3844.794 | I31: =MIN(I30,$E$2) -> 4000 | ... M31: =MIN(M30,$E$2) -> 4000 | N31: =SUM(B31:M31) -> 47321.443
A32: Extra donuts(over) | B32: =IF(B30<$E$2,$E$2-B30,0) -> 447.3226 | C32: =IF(C30<$E$2,$E$2-C30,0) -> 0 | D32: =IF(D30<$E$2,$E$2-D30,0) -> 76.028491 | E32: =IF(E30<$E$2,$E$2-E30,0) -> 0 | F32: =IF(F30<$E$2,$E$2-F30,0) -> 0 | G32: =IF(G30<$E$2,$E$2-G30,0) -> 0 | H32: =IF(H30<$E$2,$E$2-H30,0) -> 155.20598 | I32: =IF(I30<$E$2,$E$2-I30,0) -> 0 | ... M32: =IF(M30<$E$2,$E$2-M30,0) -> 0 | N32: =SUM(B32:M32) -> 678.55706
A33: Unsatisfied customers (short) | B33: =IF(B30>$E$2,B30-$E$2,0) -> 0 | C33: =IF(C30>$E$2,C30-$E$2,0) -> 90.911689 | D33: =IF(D30>$E$2,D30-$E$2,0) -> 0 | E33: =IF(E30>$E$2,E30-$E$2,0) -> 1029.3225 | F33: =IF(F30>$E$2,F30-$E$2,0) -> 1428.4191 | G33: =IF(G30>$E$2,G30-$E$2,0) -> 1084.0183 | H33: =IF(H30>$E$2,H30-$E$2,0) -> 0 | I33: =IF(I30>$E$2,I30-$E$2,0) -> 663.97833 | ... M33: =IF(M30>$E$2,M30-$E$2,0) -> 3843.1543 | N33: =SUM(B33:M33) -> 12780.966
A34: Revenue
A35: coffee | B35: =B31*'Financial information 1 Pt1'!$C$7 -> 10622.505 | C35: =C31*'Financial information 1 Pt1'!$C$7 -> 11960 | D35: =D31*'Financial information 1 Pt1'!$C$7 -> 11732.675 | E35: =E31*'Financial information 1 Pt1'!$C$7 -> 11960 | F35: =F31*'Financial information 1 Pt1'!$C$7 -> 11960 | G35: =G31*'Financial information 1 Pt1'!$C$7 -> 11960 | H35: =H31*'Financial information 1 Pt1'!$C$7 -> 11495.934 | I35: =I31*'Financial information 1 Pt1'!$C$7 -> 11960 | ... M35: =M31*'Financial information 1 Pt1'!$C$7 -> 11960 | N35: =SUM(B35:M35) -> 141491.11
A36: donut | B36: =B31*'Financial information 1 Pt1'!$C$8 -> 8881.6935 | C36: =C31*'Financial information 1 Pt1'!$C$8 -> 10000 | D36: =D31*'Financial information 1 Pt1'!$C$8 -> 9809.9288 | E36: =E31*'Financial information 1 Pt1'!$C$8 -> 10000 | F36: =F31*'Financial information 1 Pt1'!$C$8 -> 10000 | G36: =G31*'Financial information 1 Pt1'!$C$8 -> 10000 | H36: =H31*'Financial information 1 Pt1'!$C$8 -> 9611.9851 | I36: =I31*'Financial information 1 Pt1'!$C$8 -> 10000 | ... M36: =M31*'Financial information 1 Pt1'!$C$8 -> 10000 | N36: =SUM(B36:M36) -> 118303.61
A37: Revenue from day old sales | B37: =B32*$G$2 -> 559.15324 | C37: =C32*$G$2 -> 0 | D37: =D32*$G$2 -> 95.035614 | E37: =E32*$G$2 -> 0 | F37: =F32*$G$2 -> 0 | G37: =G32*$G$2 -> 0 | H37: =H32*$G$2 -> 194.00747 | I37: =I32*$G$2 -> 0 | ... M37: =M32*$G$2 -> 0 | N37: =SUM(B37:M37) -> 848.19633
A38: Total Revenue | B38: =SUM(B35:B37) -> 20063.352 | C38: =SUM(C35:C37) -> 21960 | D38: =SUM(D35:D37) -> 21637.639 | E38: =SUM(E35:E37) -> 21960 | F38: =SUM(F35:F37) -> 21960 | G38: =SUM(G35:G37) -> 21960 | H38: =SUM(H35:H37) -> 21301.927 | I38: =SUM(I35:I37) -> 21960 | ... M38: =SUM(M35:M37) -> 21960 | N38: =SUM(B38:M38) -> 260642.92
A39: Expenses
A40: Fixed Expenses | B40: =GETPIVOTDATA("Expense/revenue",'Financial information 1 Pt1'!$E$5,"Profit Model label","Fixed Expense") -> 5800 | C40: =GETPIVOTDATA("Expense/revenue",'Financial information 1 Pt1'!$E$5,"Profit Model label","Fixed Expense") -> 5800 | D40: =GETPIVOTDATA("Expense/revenue",'Financial information 1 Pt1'!$E$5,"Profit Model label","Fixed Expense") -> 5800 | E40: =GETPIVOTDATA("Expense/revenue",'Financial information 1 Pt1'!$E$5,"Profit Model label","Fixed Expense") -> 5800 | F40: =GETPIVOTDATA("Expense/revenue",'Financial information 1 Pt1'!$E$5,"Profit Model label","Fixed Expense") -> 5800 | G40: =GETPIVOTDATA("Expense/revenue",'Financial information 1 Pt1'!$E$5,"Profit Model label","Fixed Expense") -> 5800 | H40: =GETPIVOTDATA("Expense/revenue",'Financial information 1 Pt1'!$E$5,"Profit Model label","Fixed Expense") -> 5800 | I40: =GETPIVOTDATA("Expense/revenue",'Financial information 1 Pt1'!$E$5,"Profit Model label","Fixed Expense") -> 5800 | ... M40: =GETPIVOTDATA("Expense/revenue",'Financial information 1 Pt1'!$E$5,"Profit Model label","Fixed Expense") -> 5800 | N40: =SUM(B40:M40) -> 69600
A41: Total Fixed Expense | B41: =GETPIVOTDATA("Expense/revenue",'Financial information 1 Pt1'!$E$5,"Profit Model label","Fixed Expense") -> 5800 | C41: =GETPIVOTDATA("Expense/revenue",'Financial information 1 Pt1'!$E$5,"Profit Model label","Fixed Expense") -> 5800 | D41: =GETPIVOTDATA("Expense/revenue",'Financial information 1 Pt1'!$E$5,"Profit Model label","Fixed Expense") -> 5800 | E41: =GETPIVOTDATA("Expense/revenue",'Financial information 1 Pt1'!$E$5,"Profit Model label","Fixed Expense") -> 5800 | F41: =GETPIVOTDATA("Expense/revenue",'Financial information 1 Pt1'!$E$5,"Profit Model label","Fixed Expense") -> 5800 | G41: =GETPIVOTDATA("Expense/revenue",'Financial information 1 Pt1'!$E$5,"Profit Model label","Fixed Expense") -> 5800 | H41: =GETPIVOTDATA("Expense/revenue",'Financial information 1 Pt1'!$E$5,"Profit Model label","Fixed Expense") -> 5800 | I41: =GETPIVOTDATA("Expense/revenue",'Financial information 1 Pt1'!$E$5,"Profit Model label","Fixed Expense") -> 5800 | ... M41: =GETPIVOTDATA("Expense/revenue",'Financial information 1 Pt1'!$E$5,"Profit Model label","Fixed Expense") -> 5800 | N41: =SUM(B41:M41) -> 69600
A43: Variable Expenses
A44: Coffee Variable expense | B44: =$E$2*GETPIVOTDATA("Expense/revenue",'Financial information 1 Pt1'!$E$5,"Profit Model label","Variable Expense: Coffee") -> 2000 | C44: =$E$2*GETPIVOTDATA("Expense/revenue",'Financial information 1 Pt1'!$E$5,"Profit Model label","Variable Expense: Coffee") -> 2000 | D44: =$E$2*GETPIVOTDATA("Expense/revenue",'Financial information 1 Pt1'!$E$5,"Profit Model label","Variable Expense: Coffee") -> 2000 | E44: =$E$2*GETPIVOTDATA("Expense/revenue",'Financial information 1 Pt1'!$E$5,"Profit Model label","Variable Expense: Coffee") -> 2000 | F44: =$E$2*GETPIVOTDATA("Expense/revenue",'Financial information 1 Pt1'!$E$5,"Profit Model label","Variable Expense: Coffee") -> 2000 | G44: =$E$2*GETPIVOTDATA("Expense/revenue",'Financial information 1 Pt1'!$E$5,"Profit Model label","Variable Expense: Coffee") -> 2000 | H44: =$E$2*GETPIVOTDATA("Expense/revenue",'Financial information 1 Pt1'!$E$5,"Profit Model label","Variable Expense: Coffee") -> 2000 | I44: =$E$2*GETPIVOTDATA("Expense/revenue",'Financial information 1 Pt1'!$E$5,"Profit Model label","Variable Expense: Coffee") -> 2000 | ... M44: =$E$2*GETPIVOTDATA("Expense/revenue",'Financial information 1 Pt1'!$E$5,"Profit Model label","Variable Expense: Coffee") -> 2000 | N44: =SUM(B44:M44) -> 24000
A45: Donut Variable expense | B45: =$E$2*GETPIVOTDATA("Expense/revenue",'Financial information 1 Pt1'!$E$5,"Profit Model label","Variable Expense: Donut") -> 2400 | C45: =$E$2*GETPIVOTDATA("Expense/revenue",'Financial information 1 Pt1'!$E$5,"Profit Model label","Variable Expense: Donut") -> 2400 | D45: =$E$2*GETPIVOTDATA("Expense/revenue",'Financial information 1 Pt1'!$E$5,"Profit Model label","Variable Expense: Donut") -> 2400 | E45: =$E$2*GETPIVOTDATA("Expense/revenue",'Financial information 1 Pt1'!$E$5,"Profit Model label","Variable Expense: Donut") -> 2400 | F45: =$E$2*GETPIVOTDATA("Expense/revenue",'Financial information 1 Pt1'!$E$5,"Profit Model label","Variable Expense: Donut") -> 2400 | G45: =$E$2*GETPIVOTDATA("Expense/revenue",'Financial information 1 Pt1'!$E$5,"Profit Model label","Variable Expense: Donut") -> 2400 | H45: =$E$2*GETPIVOTDATA("Expense/revenue",'Financial information 1 Pt1'!$E$5,"Profit Model label","Variable Expense: Donut") -> 2400 | I45: =$E$2*GETPIVOTDATA("Expense/revenue",'Financial information 1 Pt1'!$E$5,"Profit Model label","Variable Expense: Donut") -> 2400 | ... M45: =$E$2*GETPIVOTDATA("Expense/revenue",'Financial information 1 Pt1'!$E$5,"Profit Model label","Variable Expense: Donut") -> 2400 | N45: =SUM(B45:M45) -> 28800
A46: Total Variable Expenses | B46: =SUM(B44:B45) -> 4400 | C46: =SUM(C44:C45) -> 4400 | D46: =SUM(D44:D45) -> 4400 | E46: =SUM(E44:E45) -> 4400 | F46: =SUM(F44:F45) -> 4400 | G46: =SUM(G44:G45) -> 4400 | H46: =SUM(H44:H45) -> 4400 | I46: =SUM(I44:I45) -> 4400 | ... M46: =SUM(M44:M45) -> 4400 | N46: =SUM(B46:M46) -> 52800
A47: Expenses: due to lost sales | B47: =B33*$F$2 -> 0 | C47: =C33*$F$2 -> 272.73507 | D47: =D33*$F$2 -> 0 | E47: =E33*$F$2 -> 3087.9674 | F47: =F33*$F$2 -> 4285.2574 | G47: =G33*$F$2 -> 3252.055 | H47: =H33*$F$2 -> 0 | I47: =I33*$F$2 -> 1991.935 | ... M47: =M33*$F$2 -> 11529.463 | N47: =SUM(B47:M47) -> 38342.898
A48: Total Expenses | B48: =B41+B46+B47 -> 10200 | C48: =C41+C46+C47 -> 10472.735 | D48: =D41+D46+D47 -> 10200 | E48: =E41+E46+E47 -> 13287.967 | F48: =F41+F46+F47 -> 14485.257 | G48: =G41+G46+G47 -> 13452.055 | H48: =H41+H46+H47 -> 10200 | I48: =I41+I46+I47 -> 12191.935 | ... M48: =M41+M46+M47 -> 21729.463 | N48: =SUM(B48:M48) -> 160742.9
A50: Profit Donuts and Coffee | B50: =B38-B48 -> 9863.3522 | C50: =C38-C48 -> 11487.265 | D50: =D38-D48 -> 11437.639 | E50: =E38-E48 -> 8672.0326 | F50: =F38-F48 -> 7474.7426 | G50: =G38-G48 -> 8507.945 | H50: =H38-H48 -> 11101.927 | I50: =I38-I48 -> 9768.065 | ... M50: =M38-M48 -> 230.53724 | N50: =SUM(B50:M50) -> 99900.02
A53: LOW DEMAND
A54: Month | B54: =B29 -> 44927 | C54: =C29 -> 44958 | D54: =D29 -> 44986 | E54: =E29 -> 45017 | F54: =F29 -> 45047 | G54: =G29 -> 45078 | H54: =H29 -> 45108 | I54: =I29 -> 45139 | ... M54: =M29 -> 45261 | N54: Yearly Total
A55: Demand | B55: =B5*(1-'Financial information 1 Pt1'!$B$35) -> 2154.9027 | C55: =C5*(1-'Financial information 1 Pt1'!$B$35) -> 2481.3727 | D55: =D5*(1-'Financial information 1 Pt1'!$B$35) -> 2380.1139 | E55: =E5*(1-'Financial information 1 Pt1'!$B$35) -> 3050.5726 | F55: =F5*(1-'Financial information 1 Pt1'!$B$35) -> 3292.6477 | G55: =G5*(1-'Financial information 1 Pt1'!$B$35) -> 3083.7488 | H55: =H5*(1-'Financial information 1 Pt1'!$B$35) -> 2332.0882 | I55: =I5*(1-'Financial information 1 Pt1'!$B$35) -> 2828.9705 | ... M55: =M5*(1-'Financial information 1 Pt1'!$B$35) -> 4757.3231 | N55: =SUM(B55:M55) -> 36455.56
A56: satisfied demand | B56: =MIN(B55,$E$2) -> 2154.9027 | C56: =MIN(C55,$E$2) -> 2481.3727 | D56: =MIN(D55,$E$2) -> 2380.1139 | E56: =MIN(E55,$E$2) -> 3050.5726 | F56: =MIN(F55,$E$2) -> 3292.6477 | G56: =MIN(G55,$E$2) -> 3083.7488 | H56: =MIN(H55,$E$2) -> 2332.0882 | I56: =MIN(I55,$E$2) -> 2828.9705 | ... M56: =MIN(M55,$E$2) -> 4000 | N56: =SUM(B56:M56) -> 35698.237
A57: Extra donuts(over) | B57: =IF(B55<$E$2,$E$2-B55,0) -> 1845.0973 | C57: =IF(C55<$E$2,$E$2-C55,0) -> 1518.6273 | D57: =IF(D55<$E$2,$E$2-D55,0) -> 1619.8861 | E57: =IF(E55<$E$2,$E$2-E55,0) -> 949.42735 | F57: =IF(F55<$E$2,$E$2-F55,0) -> 707.35232 | G57: =IF(G55<$E$2,$E$2-G55,0) -> 916.25118 | H57: =IF(H55<$E$2,$E$2-H55,0) -> 1667.9118 | I57: =IF(I55<$E$2,$E$2-I55,0) -> 1171.0295 | ... M57: =IF(M55<$E$2,$E$2-M55,0) -> 0 | N57: =SUM(B57:M57) -> 12301.763
A58: Unsatisfied customers (short) | B58: =IF(B55>$E$2,B55-$E$2,0) -> 0 | C58: =IF(C55>$E$2,C55-$E$2,0) -> 0 | D58: =IF(D55>$E$2,D55-$E$2,0) -> 0 | E58: =IF(E55>$E$2,E55-$E$2,0) -> 0 | F58: =IF(F55>$E$2,F55-$E$2,0) -> 0 | G58: =IF(G55>$E$2,G55-$E$2,0) -> 0 | H58: =IF(H55>$E$2,H55-$E$2,0) -> 0 | I58: =IF(I55>$E$2,I55-$E$2,0) -> 0 | ... M58: =IF(M55>$E$2,M55-$E$2,0) -> 757.32307 | N58: =SUM(B58:M58) -> 757.32307
A59: Revenue
A60: coffee | B60: =B56*'Financial information 1 Pt1'!$C$7 -> 6443.159 | C60: =C56*'Financial information 1 Pt1'!$C$7 -> 7419.3043 | D60: =D56*'Financial information 1 Pt1'!$C$7 -> 7116.5405 | E60: =E56*'Financial information 1 Pt1'!$C$7 -> 9121.2122 | F60: =F56*'Financial information 1 Pt1'!$C$7 -> 9845.0166 | G60: =G56*'Financial information 1 Pt1'!$C$7 -> 9220.409 | H60: =H56*'Financial information 1 Pt1'!$C$7 -> 6972.9437 | I60: =I56*'Financial information 1 Pt1'!$C$7 -> 8458.6217 | ... M60: =M56*'Financial information 1 Pt1'!$C$7 -> 11960 | N60: =SUM(B60:M60) -> 106737.73
A61: donut | B61: =B56*'Financial information 1 Pt1'!$C$8 -> 5387.2567 | C61: =C56*'Financial information 1 Pt1'!$C$8 -> 6203.4317 | D61: =D56*'Financial information 1 Pt1'!$C$8 -> 5950.2847 | E61: =E56*'Financial information 1 Pt1'!$C$8 -> 7626.4316 | F61: =F56*'Financial information 1 Pt1'!$C$8 -> 8231.6192 | G61: =G56*'Financial information 1 Pt1'!$C$8 -> 7709.3721 | H61: =H56*'Financial information 1 Pt1'!$C$8 -> 5830.2204 | I61: =I56*'Financial information 1 Pt1'!$C$8 -> 7072.4262 | ... M61: =M56*'Financial information 1 Pt1'!$C$8 -> 10000 | N61: =SUM(B61:M61) -> 89245.591
A62: Revenue from day old sales | B62: =B57*$G$2 -> 2306.3716 | C62: =C57*$G$2 -> 1898.2842 | D62: =D57*$G$2 -> 2024.8577 | E62: =E57*$G$2 -> 1186.7842 | F62: =F57*$G$2 -> 884.1904 | G62: =G57*$G$2 -> 1145.314 | H62: =H57*$G$2 -> 2084.8898 | I62: =I57*$G$2 -> 1463.7869 | ... M62: =M57*$G$2 -> 0 | N62: =SUM(B62:M62) -> 15377.204
A63: Total Revenue | B63: =SUM(B60:B62) -> 14136.787 | C63: =SUM(C60:C62) -> 15521.02 | D63: =SUM(D60:D62) -> 15091.683 | E63: =SUM(E60:E62) -> 17934.428 | F63: =SUM(F60:F62) -> 18960.826 | G63: =SUM(G60:G62) -> 18075.095 | H63: =SUM(H60:H62) -> 14888.054 | I63: =SUM(I60:I62) -> 16994.835 | ... M63: =SUM(M60:M62) -> 21960 | N63: =SUM(B63:M63) -> 211360.52
A64: Expenses
A65: Fixed Expenses | B65: =GETPIVOTDATA("Expense/revenue",'Financial information 1 Pt1'!$E$5,"Profit Model label","Fixed Expense") -> 5800 | C65: =GETPIVOTDATA("Expense/revenue",'Financial information 1 Pt1'!$E$5,"Profit Model label","Fixed Expense") -> 5800 | D65: =GETPIVOTDATA("Expense/revenue",'Financial information 1 Pt1'!$E$5,"Profit Model label","Fixed Expense") -> 5800 | E65: =GETPIVOTDATA("Expense/revenue",'Financial information 1 Pt1'!$E$5,"Profit Model label","Fixed Expense") -> 5800 | F65: =GETPIVOTDATA("Expense/revenue",'Financial information 1 Pt1'!$E$5,"Profit Model label","Fixed Expense") -> 5800 | G65: =GETPIVOTDATA("Expense/revenue",'Financial information 1 Pt1'!$E$5,"Profit Model label","Fixed Expense") -> 5800 | H65: =GETPIVOTDATA("Expense/revenue",'Financial information 1 Pt1'!$E$5,"Profit Model label","Fixed Expense") -> 5800 | I65: =GETPIVOTDATA("Expense/revenue",'Financial information 1 Pt1'!$E$5,"Profit Model label","Fixed Expense") -> 5800 | ... M65: =GETPIVOTDATA("Expense/revenue",'Financial information 1 Pt1'!$E$5,"Profit Model label","Fixed Expense") -> 5800 | N65: =SUM(B65:M65) -> 69600
A66: Total Fixed Expense | B66: =GETPIVOTDATA("Expense/revenue",'Financial information 1 Pt1'!$E$5,"Profit Model label","Fixed Expense") -> 5800 | C66: =GETPIVOTDATA("Expense/revenue",'Financial information 1 Pt1'!$E$5,"Profit Model label","Fixed Expense") -> 5800 | D66: =GETPIVOTDATA("Expense/revenue",'Financial information 1 Pt1'!$E$5,"Profit Model label","Fixed Expense") -> 5800 | E66: =GETPIVOTDATA("Expense/revenue",'Financial information 1 Pt1'!$E$5,"Profit Model label","Fixed Expense") -> 5800 | F66: =GETPIVOTDATA("Expense/revenue",'Financial information 1 Pt1'!$E$5,"Profit Model label","Fixed Expense") -> 5800 | G66: =GETPIVOTDATA("Expense/revenue",'Financial information 1 Pt1'!$E$5,"Profit Model label","Fixed Expense") -> 5800 | H66: =GETPIVOTDATA("Expense/revenue",'Financial information 1 Pt1'!$E$5,"Profit Model label","Fixed Expense") -> 5800 | I66: =GETPIVOTDATA("Expense/revenue",'Financial information 1 Pt1'!$E$5,"Profit Model label","Fixed Expense") -> 5800 | ... M66: =GETPIVOTDATA("Expense/revenue",'Financial information 1 Pt1'!$E$5,"Profit Model label","Fixed Expense") -> 5800 | N66: =SUM(B66:M66) -> 69600
A68: Variable Expenses
A69: Coffee Variable expense | B69: =$E$2*GETPIVOTDATA("Expense/revenue",'Financial information 1 Pt1'!$E$5,"Profit Model label","Variable Expense: Coffee") -> 2000 | C69: =$E$2*GETPIVOTDATA("Expense/revenue",'Financial information 1 Pt1'!$E$5,"Profit Model label","Variable Expense: Coffee") -> 2000 | D69: =$E$2*GETPIVOTDATA("Expense/revenue",'Financial information 1 Pt1'!$E$5,"Profit Model label","Variable Expense: Coffee") -> 2000 | E69: =$E$2*GETPIVOTDATA("Expense/revenue",'Financial information 1 Pt1'!$E$5,"Profit Model label","Variable Expense: Coffee") -> 2000 | F69: =$E$2*GETPIVOTDATA("Expense/revenue",'Financial information 1 Pt1'!$E$5,"Profit Model label","Variable Expense: Coffee") -> 2000 | G69: =$E$2*GETPIVOTDATA("Expense/revenue",'Financial information 1 Pt1'!$E$5,"Profit Model label","Variable Expense: Coffee") -> 2000 | H69: =$E$2*GETPIVOTDATA("Expense/revenue",'Financial information 1 Pt1'!$E$5,"Profit Model label","Variable Expense: Coffee") -> 2000 | I69: =$E$2*GETPIVOTDATA("Expense/revenue",'Financial information 1 Pt1'!$E$5,"Profit Model label","Variable Expense: Coffee") -> 2000 | ... M69: =$E$2*GETPIVOTDATA("Expense/revenue",'Financial information 1 Pt1'!$E$5,"Profit Model label","Variable Expense: Coffee") -> 2000 | N69: =SUM(B69:M69) -> 24000
A70: Donut Variable expense | B70: =$E$2*GETPIVOTDATA("Expense/revenue",'Financial information 1 Pt1'!$E$5,"Profit Model label","Variable Expense: Donut") -> 2400 | C70: =$E$2*GETPIVOTDATA("Expense/revenue",'Financial information 1 Pt1'!$E$5,"Profit Model label","Variable Expense: Donut") -> 2400 | D70: =$E$2*GETPIVOTDATA("Expense/revenue",'Financial information 1 Pt1'!$E$5,"Profit Model label","Variable Expense: Donut") -> 2400 | E70: =$E$2*GETPIVOTDATA("Expense/revenue",'Financial information 1 Pt1'!$E$5,"Profit Model label","Variable Expense: Donut") -> 2400 | F70: =$E$2*GETPIVOTDATA("Expense/revenue",'Financial information 1 Pt1'!$E$5,"Profit Model label","Variable Expense: Donut") -> 2400 | G70: =$E$2*GETPIVOTDATA("Expense/revenue",'Financial information 1 Pt1'!$E$5,"Profit Model label","Variable Expense: Donut") -> 2400 | H70: =$E$2*GETPIVOTDATA("Expense/revenue",'Financial information 1 Pt1'!$E$5,"Profit Model label","Variable Expense: Donut") -> 2400 | I70: =$E$2*GETPIVOTDATA("Expense/revenue",'Financial information 1 Pt1'!$E$5,"Profit Model label","Variable Expense: Donut") -> 2400 | ... M70: =$E$2*GETPIVOTDATA("Expense/revenue",'Financial information 1 Pt1'!$E$5,"Profit Model label","Variable Expense: Donut") -> 2400 | N70: =SUM(B70:M70) -> 28800
A71: Total Variable Expenses | B71: =SUM(B69:B70) -> 4400 | C71: =SUM(C69:C70) -> 4400 | D71: =SUM(D69:D70) -> 4400 | E71: =SUM(E69:E70) -> 4400 | F71: =SUM(F69:F70) -> 4400 | G71: =SUM(G69:G70) -> 4400 | H71: =SUM(H69:H70) -> 4400 | I71: =SUM(I69:I70) -> 4400 | ... M71: =SUM(M69:M70) -> 4400 | N71: =SUM(B71:M71) -> 52800
A72: Expenses: due to lost sales | B72: =B58*$F$2 -> 0 | C72: =C58*$F$2 -> 0 | D72: =D58*$F$2 -> 0 | E72: =E58*$F$2 -> 0 | F72: =F58*$F$2 -> 0 | G72: =G58*$F$2 -> 0 | H72: =H58*$F$2 -> 0 | I72: =I58*$F$2 -> 0 | ... M72: =M58*$F$2 -> 2271.9692 | N72: =SUM(B72:M72) -> 2271.9692
A73: Total Expenses | B73: =B66+B71+B72 -> 10200 | C73: =C66+C71+C72 -> 10200 | D73: =D66+D71+D72 -> 10200 | E73: =E66+E71+E72 -> 10200 | F73: =F66+F71+F72 -> 10200 | G73: =G66+G71+G72 -> 10200 | H73: =H66+H71+H72 -> 10200 | I73: =I66+I71+I72 -> 10200 | ... M73: =M66+M71+M72 -> 12471.969 | N73: =SUM(B73:M73) -> 124671.97
A75: Profit Donuts and Coffee | B75: =B63-B73 -> 3936.7874 | C75: =C63-C73 -> 5321.0201 | D75: =D63-D73 -> 4891.6828 | E75: =E63-E73 -> 7734.428 | F75: =F63-F73 -> 8760.8262 | G75: =G63-G73 -> 7875.095 | H75: =H63-H73 -> 4688.0539 | I75: =I63-I73 -> 6794.8348 | ... M75: =M63-M73 -> 9488.0308 | N75: =SUM(B75:M75) -> 86688.554
Z200: Ahadu Solomon
Z201: Spring 2021

Sheet Expected Values Pt4
A1: Remember that we use profits to fill in payoff tables like the ones we forecasted in the previous sheets. It would help if you filled in the table in C5:E7 and referenced those values to the other tables below. Use the probabilities found in Financial Information B42:44 for the regret tables | B1: PAYOFF TABLE | C1: Reminder: Format Cells to show 2 decimal places
I2: Fill in the space below for each method solved under each Decision Alternative. This is just a summary of the results on the left.
C3: State of Nature | H3: Summary of Results | I3: Methods
B4: Decision Alternatives | C4: Low | D4: Average | E4: High | H4: =B4 -> Decision Alternatives | I4: Maximin | J4: MaxiMax | K4: Laplace | L4: MinMax regret | M4: EVUII | N4: EOL
B5: CURRENT OPERATIONS | C5: ='Current operations Pt3 '!N75 -> 86688.554 | D5: ='Current operations Pt3 '!N25 -> 111605.66 | E5: ='Current operations Pt3 '!N50 -> 99900.02 | H5: CURRENT OPERATIONS | I5: =MIN(C13:E13) -> 86688.554 | J5: =MAX(C20:E20) -> 111605.66 | K5: =AVERAGE(C27:E27) -> 99398.076 | L5: =MAX(C34:E34) -> 10817.34 | M5: =SUMPRODUCT(C42:E42,C43:E43) -> 103695.83 | N5: =SUMPRODUCT(C58:E58,C59:E59) -> 4094.4223
B6: FRANCHISE | C6: ='Franchise operations Pt3'!N75 -> 72488.04 | D6: ='Franchise operations Pt3'!N25 -> 114133.09 | E6: ='Franchise operations Pt3'!N50 -> 109681.03 | H6: FRANCHISE | I6: =MIN(C14:E14) -> 72488.04 | J6: =MAX(C21:E21) -> 114133.09 | K6: =AVERAGE(C28:E28) -> 98767.385 | L6: =MAX(C35:E35) -> 14200.514 | M6: =SUMPRODUCT(C42:E42,C44:E44) -> 104691.06 | N6: =SUMPRODUCT(C58:E58,C60:E60) -> 3099.1854
B7: FOOD TRUCK | C7: ='Food Truck Pt 4'!N75 -> 60155.663 | D7: ='Food Truck Pt 4'!N25 -> 109752.02 | E7: ='Food Truck Pt 4'!N50 -> 110717.36 | H7: FOOD TRUCK | I7: =MIN(C15:E15) -> 60155.663 | J7: =MAX(C22:E22) -> 110717.36 | K7: =AVERAGE(C29:E29) -> 93541.681 | L7: =MAX(C36:E36) -> 26532.891 | M7: =SUMPRODUCT(C42:E42,C45:E45) -> 100074.08 | N7: =SUMPRODUCT(C58:E58,C61:E61) -> 7716.1644
B9: DM UNDER IGNORANCE | H9: Kiana should choose to:
B10: Maximin | H10: =H5 -> CURRENT OPERATIONS
C11: State of Nature
B12: Decision Alternatives | C12: Low | D12: Average | E12: High
B13: CURRENT OPERATIONS | C13: =C5 -> 86688.554 | D13: =D5 -> 111605.66 | E13: =E5 -> 99900.02
B14: FRANCHISE | C14: =C6 -> 72488.04 | D14: =D6 -> 114133.09 | E14: =E6 -> 109681.03
B15: FOOD TRUCK | C15: =C7 -> 60155.663 | D15: =D7 -> 109752.02 | E15: =E7 -> 110717.36
B17: Maximax
C18: State of Nature
B19: Decision Alternatives | C19: Low | D19: Average | E19: High
B20: CURRENT OPERATIONS | C20: =C13 -> 86688.554 | D20: =D13 -> 111605.66 | E20: =E13 -> 99900.02
B21: FRANCHISE | C21: =C14 -> 72488.04 | D21: =D14 -> 114133.09 | E21: =E14 -> 109681.03
B22: FOOD TRUCK | C22: =C15 -> 60155.663 | D22: =D15 -> 109752.02 | E22: =E15 -> 110717.36
B24: Laplace
C25: State of Nature
B26: Decision Alternatives | C26: Low | D26: Average | E26: High
B27: CURRENT OPERATIONS | C27: =C20 -> 86688.554 | D27: =D20 -> 111605.66 | E27: =E20 -> 99900.02 | F27: =AVERAGE(C27:E27) -> 99398.076 | G27: =MAX(F27:F29) -> 99398.076
B28: FRANCHISE | C28: =C21 -> 72488.04 | D28: =D21 -> 114133.09 | E28: =E21 -> 109681.03 | F28: =AVERAGE(C28:E28) -> 98767.385
B29: FOOD TRUCK | C29: =C22 -> 60155.663 | D29: =D22 -> 109752.02 | E29: =E22 -> 110717.36 | F29: =AVERAGE(C29:E29) -> 93541.681
B31: Minimax Regret
B32: Regret table | C32: State of Nature
B33: Decision Alternatives | C33: Low | D33: Average | E33: High
B34: CURRENT OPERATIONS | C34: =MAX(C$5:C$7)-C5 -> 0 | D34: =MAX(D$5:D$7)-D5 -> 2527.4317 | E34: =MAX(E$5:E$7)-E5 -> 10817.34
B35: FRANCHISE | C35: =MAX(C$5:C$7)-C6 -> 14200.514 | D35: =MAX(D$5:D$7)-D6 -> 0 | E35: =MAX(E$5:E$7)-E6 -> 1036.3305
B36: FOOD TRUCK | C36: =MAX(C$5:C$7)-C7 -> 26532.891 | D36: =MAX(D$5:D$7)-D7 -> 4381.0657 | E36: =MAX(E$5:E$7)-E7 -> 0
B38: DM UNDER RISK
B39: EVUII
C40: State of Nature
B41: Decision Alternatives | C41: Low | D41: Average | E41: High
B42: Probability | C42: ='Financial information 1 Pt1'!B41 -> 0.2 | D42: ='Financial information 1 Pt1'!B42 -> 0.55 | E42: ='Financial information 1 Pt1'!B43 -> 0.25
B43: CURRENT OPERATIONS | C43: =C5 -> 86688.554 | D43: =D5 -> 111605.66 | E43: =E5 -> 99900.02
B44: FRANCHISE | C44: =C6 -> 72488.04 | D44: =D6 -> 114133.09 | E44: =E6 -> 109681.03
B45: FOOD TRUCK | C45: =C7 -> 60155.663 | D45: =D7 -> 109752.02 | E45: =E7 -> 110717.36
B47: EVUPI
C48: State of Nature
B49: Decision Alternatives | C49: Low | D49: Average | E49: High
B50: Probability | C50: =C42 -> 0.2 | D50: =D42 -> 0.55 | E50: =E42 -> 0.25 | F50: =SUMPRODUCT(C50:E50,C51:E51) -> 107790.25
B51: Payoff | C51: =MAX(C43:C45) -> 86688.554 | D51: =MAX(D43:D45) -> 114133.09 | E51: =MAX(E43:E45) -> 110717.36
B53: EVPI | C53: =F50-M6 -> 3099.1854
B55: EOL
B56: Regret table | C56: State of Nature
B57: Decision Alternatives | C57: Low | D57: Average | E57: High
B58: Probability | C58: =C42 -> 0.2 | D58: =D42 -> 0.55 | E58: =E42 -> 0.25
B59: CURRENT OPERATIONS | C59: =C34 -> 0 | D59: =D34 -> 2527.4317 | E59: =E34 -> 10817.34
B60: FRANCHISE | C60: =C35 -> 14200.514 | D60: =D35 -> 0 | E60: =E35 -> 1036.3305
B61: FOOD TRUCK | C61: =C36 -> 26532.891 | D61: =D36 -> 4381.0657 | E61: =E36 -> 0

Sheet Financial information 1 Pt1
A1: Donut Information
A2: Based on the below data, create the profit model for Donuts to Go.
A3: Assume that each customer will buy one donut and one cup of coffee
E5: Row Labels | F5: Sum of Expense/revenue
A6: Item | B6: Profit Model label | C6: Expense/revenue | E6: Fixed Expense | F6: 5800
A7: Revenue: Cup of Coffee | B7: Rev: Coffee | C7: 2.99 | E7: Rev: Coffee | F7: 2.99
A8: Revenue: Donut | B8: Rev: Donut | C8: 2.5 | E8: Rev: Donut | F8: 2.5
A9: Donut ingredients per donunt) | B9: Variable Expense: Donut | C9: 0.5 | E9: Variable Expense: Coffee | F9: 0.5
A10: paper products: napkins, plates etc per Donut | B10: Variable Expense: Donut | C10: 0.1 | E10: Variable Expense: Donut | F10: 0.6
A11: Insurance | B11: Fixed Expense | C11: 300 | E11: Grand Total | F11: 5806.59
A12: Maintenance & Repairs to equipment | B12: Fixed Expense | C12: 0
A13: Marketing & Promotion: Advertising | B13: Fixed Expense | C13: 100
A14: Coffee | B14: Variable Expense: Coffee | C14: 0.35
A15: Coffee cups | B15: Variable Expense: Coffee | C15: 0.15
A16: Payroll: Wages (Owner/ Manager) | B16: Fixed Expense | C16: 2400
A17: Payroll: Wages (per Employees) | B17: Fixed Expense | C17: 1200 | E17: Row Labels | F17: Sum of Expense/revenue
A18: Donut and Coffee equipment rent | B18: Fixed Expense | C18: 500 | E18: Fixed Expense | F18: 5800
A19: Professional Fees: Accounting | B19: Fixed Expense | C19: 50 | E19: Rev: Coffee | F19: 2.99
A20: Professional Fees: Legal | B20: Fixed Expense | C20: 25 | E20: Rev: Donut | F20: 2.5
A21: Powdered and Liquid Beverages | B21: Fixed Expense | C21: 0 | E21: Variable Expense: Coffee | F21: 0.5
A22: Rent | B22: Fixed Expense | C22: 1000 | E22: Variable Expense: Donut | F22: 0.6
A23: Supplies: Office | B23: Fixed Expense | C23: 25 | E23: Grand Total | F23: 5806.59
A24: Utilities | B24: Fixed Expense | C24: 200
A29: Additional Data
A30: Operations
A31: Monthly Production | B31: 4000
A32: Lost Sales | B32: 3
A33: Day old revenue | B33: 1.25
A34: High demand, % above Average | B34: 0.22
A35: Low Demand, % below average | B35: 0.26
A36: Franchise Operations
A37: Monthly Fixed Expense increase | B37: 4350
A38: Monthly Production Increase | B38: 0.32
A39: Monthly demand increase | B39: 0.22
A40: States of Natures | B40: probabilities
A41: Low | B41: 0.2
A42: Average demand | B42: 0.55
A43: High | B43: 0.25
A61: Total

Sheet Food Truck  Pt 4
A1: Food Truck | B1: Reminder: Format Cells to show 2 decimal places | E1: MAKE to Order
A2: Part 4
A3: AVERAGE DEMAND
A4: Month | B4: 44927 | C4: 44958 | D4: 44986 | E4: 45017 | F4: 45047 | G4: 45078 | H4: 45108 | I4: 45139 | J4: 45170 | K4: 45200 | L4: 45231 | M4: 45261 | N4: Yearly Total
A5: Demand | B5: ='Food Truck Demand'!B17 -> 1949.7956 | C5: ='Food Truck Demand'!B18 -> 2298.6423 | D5: ='Food Truck Demand'!B19 -> 2298.6423 | E5: ='Food Truck Demand'!B20 -> 2647.4891 | F5: ='Food Truck Demand'!B21 -> 2647.4891 | G5: ='Food Truck Demand'!B22 -> 3654.3723 | H5: ='Food Truck Demand'!B23 -> 3654.3723 | I5: ='Food Truck Demand'!B24 -> 2647.4891 | J5: ='Food Truck Demand'!B25 -> 2996.3358 | K5: ='Food Truck Demand'!B26 -> 4003.219 | L5: ='Food Truck Demand'!B27 -> 4003.219 | M5: ='Food Truck Demand'!B28 -> 4352.0657 | N5: =SUM(B5:M5) -> 37153.131
A6: satisfied demand | B6: =B5 -> 1949.7956 | C6: =C5 -> 2298.6423 | D6: =D5 -> 2298.6423 | E6: =E5 -> 2647.4891 | F6: =F5 -> 2647.4891 | G6: =G5 -> 3654.3723 | H6: =H5 -> 3654.3723 | I6: =I5 -> 2647.4891 | ... N6: =N5 -> 37153.131
A7: Extra donuts(over) | B7: 0 | C7: 0 | D7: 0 | E7: 0 | F7: 0 | G7: 0 | H7: 0 | I7: 0 | J7: 0 | K7: 0 | L7: 0 | M7: 0 | N7: 0
A8: Unsatisfied customers (short) | B8: 0 | C8: 0 | D8: 0 | E8: 0 | F8: 0 | G8: 0 | H8: 0 | I8: 0 | J8: 0 | K8: 0 | L8: 0 | M8: 0 | N8: 0
A9: Revenue
A10: coffee | B10: =GETPIVOTDATA("Expense/revenue FT",'Financial information FT'!$I$4,"Profit Model label","Rev: Coffee")*B6 -> 5829.8889 | C10: =GETPIVOTDATA("Expense/revenue FT",'Financial information FT'!$I$4,"Profit Model label","Rev: Coffee")*C6 -> 6872.9406 | D10: =GETPIVOTDATA("Expense/revenue FT",'Financial information FT'!$I$4,"Profit Model label","Rev: Coffee")*D6 -> 6872.9406 | E10: =GETPIVOTDATA("Expense/revenue FT",'Financial information FT'!$I$4,"Profit Model label","Rev: Coffee")*E6 -> 7915.9923 | F10: =GETPIVOTDATA("Expense/revenue FT",'Financial information FT'!$I$4,"Profit Model label","Rev: Coffee")*F6 -> 7915.9923 | G10: =GETPIVOTDATA("Expense/revenue FT",'Financial information FT'!$I$4,"Profit Model label","Rev: Coffee")*G6 -> 10926.573 | H10: =GETPIVOTDATA("Expense/revenue FT",'Financial information FT'!$I$4,"Profit Model label","Rev: Coffee")*H6 -> 10926.573 | I10: =GETPIVOTDATA("Expense/revenue FT",'Financial information FT'!$I$4,"Profit Model label","Rev: Coffee")*I6 -> 7915.9923 | ... M10: =GETPIVOTDATA("Expense/revenue FT",'Financial information FT'!$I$4,"Profit Model label","Rev: Coffee")*M6 -> 13012.676 | N10: =SUM(B10:M10) -> 111087.86
A11: donut | B11: =GETPIVOTDATA("Expense/revenue FT",'Financial information FT'!$I$4,"Profit Model label","Rev: Donut")*B6 -> 4874.4891 | C11: =GETPIVOTDATA("Expense/revenue FT",'Financial information FT'!$I$4,"Profit Model label","Rev: Donut")*C6 -> 5746.6058 | D11: =GETPIVOTDATA("Expense/revenue FT",'Financial information FT'!$I$4,"Profit Model label","Rev: Donut")*D6 -> 5746.6058 | E11: =GETPIVOTDATA("Expense/revenue FT",'Financial information FT'!$I$4,"Profit Model label","Rev: Donut")*E6 -> 6618.7226 | F11: =GETPIVOTDATA("Expense/revenue FT",'Financial information FT'!$I$4,"Profit Model label","Rev: Donut")*F6 -> 6618.7226 | G11: =GETPIVOTDATA("Expense/revenue FT",'Financial information FT'!$I$4,"Profit Model label","Rev: Donut")*G6 -> 9135.9307 | H11: =GETPIVOTDATA("Expense/revenue FT",'Financial information FT'!$I$4,"Profit Model label","Rev: Donut")*H6 -> 9135.9307 | I11: =GETPIVOTDATA("Expense/revenue FT",'Financial information FT'!$I$4,"Profit Model label","Rev: Donut")*I6 -> 6618.7226 | ... M11: =GETPIVOTDATA("Expense/revenue FT",'Financial information FT'!$I$4,"Profit Model label","Rev: Donut")*M6 -> 10880.164 | N11: =SUM(B11:M11) -> 92882.828
A12: Revenue from day old sales | B12: =0 -> 0 | C12: =0 -> 0 | D12: =0 -> 0 | E12: =0 -> 0 | F12: =0 -> 0 | G12: =0 -> 0 | H12: =0 -> 0 | I12: =0 -> 0 | ... M12: =0 -> 0 | N12: =SUM(B12:M12) -> 0
A13: Total Revenue | B13: =SUM(B10:B12) -> 10704.378 | C13: =SUM(C10:C12) -> 12619.546 | D13: =SUM(D10:D12) -> 12619.546 | E13: =SUM(E10:E12) -> 14534.715 | F13: =SUM(F10:F12) -> 14534.715 | G13: =SUM(G10:G12) -> 20062.504 | H13: =SUM(H10:H12) -> 20062.504 | I13: =SUM(I10:I12) -> 14534.715 | ... N13: =SUM(N10:N12) -> 203970.69
A14: Expenses
A15: Fixed Expenses | B15: =GETPIVOTDATA("Expense/revenue FT",'Financial information FT'!$I$4,"Profit Model label","Fixed Expense") -> 5045 | C15: =GETPIVOTDATA("Expense/revenue FT",'Financial information FT'!$I$4,"Profit Model label","Fixed Expense") -> 5045 | D15: =GETPIVOTDATA("Expense/revenue FT",'Financial information FT'!$I$4,"Profit Model label","Fixed Expense") -> 5045 | E15: =GETPIVOTDATA("Expense/revenue FT",'Financial information FT'!$I$4,"Profit Model label","Fixed Expense") -> 5045 | F15: =GETPIVOTDATA("Expense/revenue FT",'Financial information FT'!$I$4,"Profit Model label","Fixed Expense") -> 5045 | G15: =GETPIVOTDATA("Expense/revenue FT",'Financial information FT'!$I$4,"Profit Model label","Fixed Expense") -> 5045 | H15: =GETPIVOTDATA("Expense/revenue FT",'Financial information FT'!$I$4,"Profit Model label","Fixed Expense") -> 5045 | I15: =GETPIVOTDATA("Expense/revenue FT",'Financial information FT'!$I$4,"Profit Model label","Fixed Expense") -> 5045 | ... M15: =GETPIVOTDATA("Expense/revenue FT",'Financial information FT'!$I$4,"Profit Model label","Fixed Expense") -> 5045 | N15: =SUM(B15:M15) -> 60540
A16: Total Fixed Expense | B16: =GETPIVOTDATA("Expense/revenue FT",'Financial information FT'!$I$4,"Profit Model label","Fixed Expense") -> 5045 | C16: =GETPIVOTDATA("Expense/revenue FT",'Financial information FT'!$I$4,"Profit Model label","Fixed Expense") -> 5045 | D16: =GETPIVOTDATA("Expense/revenue FT",'Financial information FT'!$I$4,"Profit Model label","Fixed Expense") -> 5045 | E16: =GETPIVOTDATA("Expense/revenue FT",'Financial information FT'!$I$4,"Profit Model label","Fixed Expense") -> 5045 | F16: =GETPIVOTDATA("Expense/revenue FT",'Financial information FT'!$I$4,"Profit Model label","Fixed Expense") -> 5045 | G16: =GETPIVOTDATA("Expense/revenue FT",'Financial information FT'!$I$4,"Profit Model label","Fixed Expense") -> 5045 | H16: =GETPIVOTDATA("Expense/revenue FT",'Financial information FT'!$I$4,"Profit Model label","Fixed Expense") -> 5045 | I16: =GETPIVOTDATA("Expense/revenue FT",'Financial information FT'!$I$4,"Profit Model label","Fixed Expense") -> 5045 | ... M16: =GETPIVOTDATA("Expense/revenue FT",'Financial information FT'!$I$4,"Profit Model label","Fixed Expense") -> 5045 | N16: =SUM(B16:M16) -> 60540
A18: Variable Expenses
A19: Coffee Variable expense | B19: =GETPIVOTDATA("Expense/revenue FT",'Financial information FT'!$I$4,"Profit Model label","Variable Expense coffee")*B6 -> 974.89781 | C19: =GETPIVOTDATA("Expense/revenue FT",'Financial information FT'!$I$4,"Profit Model label","Variable Expense coffee")*C6 -> 1149.3212 | D19: =GETPIVOTDATA("Expense/revenue FT",'Financial information FT'!$I$4,"Profit Model label","Variable Expense coffee")*D6 -> 1149.3212 | E19: =GETPIVOTDATA("Expense/revenue FT",'Financial information FT'!$I$4,"Profit Model label","Variable Expense coffee")*E6 -> 1323.7445 | F19: =GETPIVOTDATA("Expense/revenue FT",'Financial information FT'!$I$4,"Profit Model label","Variable Expense coffee")*F6 -> 1323.7445 | G19: =GETPIVOTDATA("Expense/revenue FT",'Financial information FT'!$I$4,"Profit Model label","Variable Expense coffee")*G6 -> 1827.1861 | H19: =GETPIVOTDATA("Expense/revenue FT",'Financial information FT'!$I$4,"Profit Model label","Variable Expense coffee")*H6 -> 1827.1861 | I19: =GETPIVOTDATA("Expense/revenue FT",'Financial information FT'!$I$4,"Profit Model label","Variable Expense coffee")*I6 -> 1323.7445 | ... M19: =GETPIVOTDATA("Expense/revenue FT",'Financial information FT'!$I$4,"Profit Model label","Variable Expense coffee")*M6 -> 2176.0328 | N19: =SUM(B19:M19) -> 18576.566
A20: Donut Variable expense | B20: =GETPIVOTDATA("Expense/revenue FT",'Financial information FT'!$I$4,"Profit Model label","Variable Expense donut")*B6 -> 1169.8774 | C20: =GETPIVOTDATA("Expense/revenue FT",'Financial information FT'!$I$4,"Profit Model label","Variable Expense donut")*C6 -> 1379.1854 | D20: =GETPIVOTDATA("Expense/revenue FT",'Financial information FT'!$I$4,"Profit Model label","Variable Expense donut")*D6 -> 1379.1854 | E20: =GETPIVOTDATA("Expense/revenue FT",'Financial information FT'!$I$4,"Profit Model label","Variable Expense donut")*E6 -> 1588.4934 | F20: =GETPIVOTDATA("Expense/revenue FT",'Financial information FT'!$I$4,"Profit Model label","Variable Expense donut")*F6 -> 1588.4934 | G20: =GETPIVOTDATA("Expense/revenue FT",'Financial information FT'!$I$4,"Profit Model label","Variable Expense donut")*G6 -> 2192.6234 | H20: =GETPIVOTDATA("Expense/revenue FT",'Financial information FT'!$I$4,"Profit Model label","Variable Expense donut")*H6 -> 2192.6234 | I20: =GETPIVOTDATA("Expense/revenue FT",'Financial information FT'!$I$4,"Profit Model label","Variable Expense donut")*I6 -> 1588.4934 | ... M20: =GETPIVOTDATA("Expense/revenue FT",'Financial information FT'!$I$4,"Profit Model label","Variable Expense donut")*M6 -> 2611.2394 | N20: =SUM(B20:M20) -> 22291.879
A21: Total Variable Expenses | B21: =SUM(B19:B20) -> 2144.7752 | C21: =SUM(C19:C20) -> 2528.5066 | D21: =SUM(D19:D20) -> 2528.5066 | E21: =SUM(E19:E20) -> 2912.238 | F21: =SUM(F19:F20) -> 2912.238 | G21: =SUM(G19:G20) -> 4019.8095 | H21: =SUM(H19:H20) -> 4019.8095 | I21: =SUM(I19:I20) -> 2912.238 | ... M21: =SUM(M19:M20) -> 4787.2723 | N21: =SUM(B21:M21) -> 40868.445
A22: Expenses: due to lost sales | B22: =0 -> 0 | C22: =0 -> 0 | D22: =0 -> 0 | E22: =0 -> 0 | F22: =0 -> 0 | G22: =0 -> 0 | H22: =0 -> 0 | I22: =0 -> 0 | ... N22: =0 -> 0
A23: Total Expenses | C23: =C16+C21+C22 -> 7573.5066 | D23: =D16+D21+D22 -> 7573.5066 | E23: =E16+E21+E22 -> 7957.238 | F23: =F16+F21+F22 -> 7957.238 | G23: =G16+G21+G22 -> 9064.8095 | H23: =H16+H21+H22 -> 9064.8095 | I23: =I16+I21+I22 -> 7957.238 | J23: =J16+J21+J22 -> 8340.9693 | ... M23: =M16+M21+M22 -> 9832.2723 | N23: =SUM(B23:M23) -> 94218.669
A25: Profit Donuts and Coffee | B25: =B13-B23 -> 10704.378 | C25: =C13-C23 -> 5046.0399 | D25: =D13-D23 -> 5046.0399 | E25: =E13-E23 -> 6577.4769 | F25: =F13-F23 -> 6577.4769 | G25: =G13-G23 -> 10997.694 | H25: =H13-H23 -> 10997.694 | I25: =I13-I23 -> 6577.4769 | ... M25: =M13-M23 -> 14060.568 | N25: =SUM(B25:M25) -> 109752.02
B27: You should be able to copy from average to high and low and then just make some modifications
A28: HIGH DEMAND
A29: Month | B29: =B4 -> 44927 | C29: =C4 -> 44958 | D29: =D4 -> 44986 | E29: =E4 -> 45017 | F29: =F4 -> 45047 | G29: =G4 -> 45078 | H29: =H4 -> 45108 | I29: =I4 -> 45139 | ... M29: =M4 -> 45261 | N29: Yearly Total
A30: Demand | B30: =B5*(1+'Financial information FT'!$B$35) -> 2047.2854 | C30: =C5*(1+'Financial information FT'!$B$35) -> 2413.5745 | D30: =D5*(1+'Financial information FT'!$B$35) -> 2413.5745 | E30: =E5*(1+'Financial information FT'!$B$35) -> 2779.8635 | F30: =F5*(1+'Financial information FT'!$B$35) -> 2779.8635 | G30: =G5*(1+'Financial information FT'!$B$35) -> 3837.0909 | H30: =H5*(1+'Financial information FT'!$B$35) -> 3837.0909 | I30: =I5*(1+'Financial information FT'!$B$35) -> 2779.8635 | ... M30: =M5*(1+'Financial information FT'!$B$35) -> 4569.669 | N30: =SUM(B30:M30) -> 39010.788
A31: satisfied demand | B31: =B30 -> 2047.2854 | C31: =C30 -> 2413.5745 | D31: =D30 -> 2413.5745 | E31: =E30 -> 2779.8635 | F31: =F30 -> 2779.8635 | G31: =G30 -> 3837.0909 | H31: =H30 -> 3837.0909 | I31: =I30 -> 2779.8635 | ... M31: =M30 -> 4569.669 | N31: =SUM(B31:M31) -> 39010.788
A32: Extra donuts(over) | B32: =IF(B30<$E$2,$E$2-B30,0) -> 0 | C32: =IF(C30<$E$2,$E$2-C30,0) -> 0 | D32: =IF(D30<$E$2,$E$2-D30,0) -> 0 | E32: =IF(E30<$E$2,$E$2-E30,0) -> 0 | F32: =IF(F30<$E$2,$E$2-F30,0) -> 0 | G32: =IF(G30<$E$2,$E$2-G30,0) -> 0 | H32: =IF(H30<$E$2,$E$2-H30,0) -> 0 | I32: =IF(I30<$E$2,$E$2-I30,0) -> 0 | ... M32: =IF(M30<$E$2,$E$2-M30,0) -> 0 | N32: =SUM(B32:M32) -> 0
A33: Unsatisfied customers (short) | B33: =0 -> 0 | C33: =0 -> 0 | D33: =0 -> 0 | E33: =0 -> 0 | F33: =0 -> 0 | G33: =0 -> 0 | H33: =0 -> 0 | I33: =0 -> 0 | ... M33: =0 -> 0 | N33: =SUM(B33:M33) -> 0
A34: Revenue
A35: coffee | B35: =B31*GETPIVOTDATA("Expense/revenue FT",'Financial information FT'!$I$4,"Profit Model label","Rev: Coffee") -> 6121.3834 | C35: =C31*GETPIVOTDATA("Expense/revenue FT",'Financial information FT'!$I$4,"Profit Model label","Rev: Coffee") -> 7216.5876 | D35: =D31*GETPIVOTDATA("Expense/revenue FT",'Financial information FT'!$I$4,"Profit Model label","Rev: Coffee") -> 7216.5876 | E35: =E31*GETPIVOTDATA("Expense/revenue FT",'Financial information FT'!$I$4,"Profit Model label","Rev: Coffee") -> 8311.7919 | F35: =F31*GETPIVOTDATA("Expense/revenue FT",'Financial information FT'!$I$4,"Profit Model label","Rev: Coffee") -> 8311.7919 | G35: =G31*GETPIVOTDATA("Expense/revenue FT",'Financial information FT'!$I$4,"Profit Model label","Rev: Coffee") -> 11472.902 | H35: =H31*GETPIVOTDATA("Expense/revenue FT",'Financial information FT'!$I$4,"Profit Model label","Rev: Coffee") -> 11472.902 | I35: =I31*GETPIVOTDATA("Expense/revenue FT",'Financial information FT'!$I$4,"Profit Model label","Rev: Coffee") -> 8311.7919 | ... M35: =M31*GETPIVOTDATA("Expense/revenue FT",'Financial information FT'!$I$4,"Profit Model label","Rev: Coffee") -> 13663.31 | N35: =SUM(B35:M35) -> 116642.26
A36: donut | B36: =B31*GETPIVOTDATA("Expense/revenue FT",'Financial information FT'!$I$4,"Profit Model label","Rev: Donut") -> 5118.2135 | C36: =C31*GETPIVOTDATA("Expense/revenue FT",'Financial information FT'!$I$4,"Profit Model label","Rev: Donut") -> 6033.9361 | D36: =D31*GETPIVOTDATA("Expense/revenue FT",'Financial information FT'!$I$4,"Profit Model label","Rev: Donut") -> 6033.9361 | E36: =E31*GETPIVOTDATA("Expense/revenue FT",'Financial information FT'!$I$4,"Profit Model label","Rev: Donut") -> 6949.6588 | F36: =F31*GETPIVOTDATA("Expense/revenue FT",'Financial information FT'!$I$4,"Profit Model label","Rev: Donut") -> 6949.6588 | G36: =G31*GETPIVOTDATA("Expense/revenue FT",'Financial information FT'!$I$4,"Profit Model label","Rev: Donut") -> 9592.7272 | H36: =H31*GETPIVOTDATA("Expense/revenue FT",'Financial information FT'!$I$4,"Profit Model label","Rev: Donut") -> 9592.7272 | I36: =I31*GETPIVOTDATA("Expense/revenue FT",'Financial information FT'!$I$4,"Profit Model label","Rev: Donut") -> 6949.6588 | ... M36: =M31*GETPIVOTDATA("Expense/revenue FT",'Financial information FT'!$I$4,"Profit Model label","Rev: Donut") -> 11424.172 | N36: =SUM(B36:M36) -> 97526.97
A37: Revenue from day old sales | B37: =B32*$G$2 -> 0 | C37: =C32*$G$2 -> 0 | D37: =D32*$G$2 -> 0 | E37: =E32*$G$2 -> 0 | F37: =F32*$G$2 -> 0 | G37: =G32*$G$2 -> 0 | H37: =H32*$G$2 -> 0 | I37: =I32*$G$2 -> 0 | ... M37: =M32*$G$2 -> 0 | N37: =SUM(B37:M37) -> 0
A38: Total Revenue | B38: =SUM(B35:B37) -> 11239.597 | C38: =SUM(C35:C37) -> 13250.524 | D38: =SUM(D35:D37) -> 13250.524 | E38: =SUM(E35:E37) -> 15261.451 | F38: =SUM(F35:F37) -> 15261.451 | G38: =SUM(G35:G37) -> 21065.629 | H38: =SUM(H35:H37) -> 21065.629 | I38: =SUM(I35:I37) -> 15261.451 | ... M38: =SUM(M35:M37) -> 25087.483 | N38: =SUM(B38:M38) -> 214169.23
A39: Expenses
A40: Fixed Expenses | B40: =GETPIVOTDATA("Expense/revenue FT",'Financial information FT'!$I$4,"Profit Model label","Fixed Expense") -> 5045 | C40: =GETPIVOTDATA("Expense/revenue FT",'Financial information FT'!$I$4,"Profit Model label","Fixed Expense") -> 5045 | D40: =GETPIVOTDATA("Expense/revenue FT",'Financial information FT'!$I$4,"Profit Model label","Fixed Expense") -> 5045 | E40: =GETPIVOTDATA("Expense/revenue FT",'Financial information FT'!$I$4,"Profit Model label","Fixed Expense") -> 5045 | F40: =GETPIVOTDATA("Expense/revenue FT",'Financial information FT'!$I$4,"Profit Model label","Fixed Expense") -> 5045 | G40: =GETPIVOTDATA("Expense/revenue FT",'Financial information FT'!$I$4,"Profit Model label","Fixed Expense") -> 5045 | H40: =GETPIVOTDATA("Expense/revenue FT",'Financial information FT'!$I$4,"Profit Model label","Fixed Expense") -> 5045 | I40: =GETPIVOTDATA("Expense/revenue FT",'Financial information FT'!$I$4,"Profit Model label","Fixed Expense") -> 5045 | ... M40: =GETPIVOTDATA("Expense/revenue FT",'Financial information FT'!$I$4,"Profit Model label","Fixed Expense") -> 5045 | N40: =SUM(B40:M40) -> 60540
A41: Total Fixed Expense | B41: =B40 -> 5045 | C41: =C40 -> 5045 | D41: =D40 -> 5045 | E41: =E40 -> 5045 | F41: =F40 -> 5045 | G41: =G40 -> 5045 | H41: =H40 -> 5045 | I41: =I40 -> 5045 | ... M41: =M40 -> 5045 | N41: =SUM(B41:M41) -> 60540
A43: Variable Expenses
A44: Coffee Variable expense | B44: =GETPIVOTDATA("Expense/revenue FT",'Financial information FT'!$I$4,"Profit Model label","Variable Expense coffee")*B31 -> 1023.6427 | C44: =GETPIVOTDATA("Expense/revenue FT",'Financial information FT'!$I$4,"Profit Model label","Variable Expense coffee")*C31 -> 1206.7872 | D44: =GETPIVOTDATA("Expense/revenue FT",'Financial information FT'!$I$4,"Profit Model label","Variable Expense coffee")*D31 -> 1206.7872 | E44: =GETPIVOTDATA("Expense/revenue FT",'Financial information FT'!$I$4,"Profit Model label","Variable Expense coffee")*E31 -> 1389.9318 | F44: =GETPIVOTDATA("Expense/revenue FT",'Financial information FT'!$I$4,"Profit Model label","Variable Expense coffee")*F31 -> 1389.9318 | G44: =GETPIVOTDATA("Expense/revenue FT",'Financial information FT'!$I$4,"Profit Model label","Variable Expense coffee")*G31 -> 1918.5454 | H44: =GETPIVOTDATA("Expense/revenue FT",'Financial information FT'!$I$4,"Profit Model label","Variable Expense coffee")*H31 -> 1918.5454 | I44: =GETPIVOTDATA("Expense/revenue FT",'Financial information FT'!$I$4,"Profit Model label","Variable Expense coffee")*I31 -> 1389.9318 | ... M44: =GETPIVOTDATA("Expense/revenue FT",'Financial information FT'!$I$4,"Profit Model label","Variable Expense coffee")*M31 -> 2284.8345 | N44: =SUM(B44:M44) -> 19505.394
A45: Donut Variable expense | B45: =GETPIVOTDATA("Expense/revenue FT",'Financial information FT'!$I$4,"Profit Model label","Variable Expense donut")*B31 -> 1228.3712 | C45: =GETPIVOTDATA("Expense/revenue FT",'Financial information FT'!$I$4,"Profit Model label","Variable Expense donut")*C31 -> 1448.1447 | D45: =GETPIVOTDATA("Expense/revenue FT",'Financial information FT'!$I$4,"Profit Model label","Variable Expense donut")*D31 -> 1448.1447 | E45: =GETPIVOTDATA("Expense/revenue FT",'Financial information FT'!$I$4,"Profit Model label","Variable Expense donut")*E31 -> 1667.9181 | F45: =GETPIVOTDATA("Expense/revenue FT",'Financial information FT'!$I$4,"Profit Model label","Variable Expense donut")*F31 -> 1667.9181 | G45: =GETPIVOTDATA("Expense/revenue FT",'Financial information FT'!$I$4,"Profit Model label","Variable Expense donut")*G31 -> 2302.2545 | H45: =GETPIVOTDATA("Expense/revenue FT",'Financial information FT'!$I$4,"Profit Model label","Variable Expense donut")*H31 -> 2302.2545 | I45: =GETPIVOTDATA("Expense/revenue FT",'Financial information FT'!$I$4,"Profit Model label","Variable Expense donut")*I31 -> 1667.9181 | ... M45: =GETPIVOTDATA("Expense/revenue FT",'Financial information FT'!$I$4,"Profit Model label","Variable Expense donut")*M31 -> 2741.8014 | N45: =SUM(B45:M45) -> 23406.473
A46: Total Variable Expenses | B46: =SUM(B44:B45) -> 2252.0139 | C46: =SUM(C44:C45) -> 2654.9319 | D46: =SUM(D44:D45) -> 2654.9319 | E46: =SUM(E44:E45) -> 3057.8499 | F46: =SUM(F44:F45) -> 3057.8499 | G46: =SUM(G44:G45) -> 4220.8 | H46: =SUM(H44:H45) -> 4220.8 | I46: =SUM(I44:I45) -> 3057.8499 | ... M46: =SUM(M44:M45) -> 5026.6359 | N46: =SUM(B46:M46) -> 42911.867
A47: Expenses: due to lost sales | B47: =0 -> 0 | C47: =0 -> 0 | D47: =0 -> 0 | E47: =0 -> 0 | F47: =0 -> 0 | G47: =0 -> 0 | H47: =0 -> 0 | I47: =0 -> 0 | ... N47: =0 -> 0
A48: Total Expenses | B48: =B41+B46+B47 -> 7297.0139 | C48: =C41+C46+C47 -> 7699.9319 | D48: =D41+D46+D47 -> 7699.9319 | E48: =E41+E46+E47 -> 8102.8499 | F48: =F41+F46+F47 -> 8102.8499 | G48: =G41+G46+G47 -> 9265.8 | H48: =H41+H46+H47 -> 9265.8 | I48: =I41+I46+I47 -> 8102.8499 | ... M48: =M41+M46+M47 -> 10071.636 | N48: =SUM(B48:M48) -> 103451.87
A50: Profit Donuts and Coffee | B50: =B38-B48 -> 3942.5829 | C50: =C38-C48 -> 5550.5918 | D50: =D38-D48 -> 5550.5918 | E50: =E38-E48 -> 7158.6008 | F50: =F38-F48 -> 7158.6008 | G50: =G38-G48 -> 11799.829 | H50: =H38-H48 -> 11799.829 | I50: =I38-I48 -> 7158.6008 | ... M50: =M38-M48 -> 15015.847 | N50: =SUM(B50:M50) -> 110717.36
A53: LOW DEMAND
A54: Month | B54: =B29 -> 44927 | C54: =C29 -> 44958 | D54: =D29 -> 44986 | E54: =E29 -> 45017 | F54: =F29 -> 45047 | G54: =G29 -> 45078 | H54: =H29 -> 45108 | I54: =I29 -> 45139 | ... M54: =M29 -> 45261 | N54: Yearly Total
A55: Demand | B55: =B5*(1-'Financial information FT'!$B$36) -> 1442.8488 | C55: =C5*(1-'Financial information FT'!$B$36) -> 1700.9953 | D55: =D5*(1-'Financial information FT'!$B$36) -> 1700.9953 | E55: =E5*(1-'Financial information FT'!$B$36) -> 1959.1419 | F55: =F5*(1-'Financial information FT'!$B$36) -> 1959.1419 | G55: =G5*(1-'Financial information FT'!$B$36) -> 2704.2355 | H55: =H5*(1-'Financial information FT'!$B$36) -> 2704.2355 | I55: =I5*(1-'Financial information FT'!$B$36) -> 1959.1419 | ... M55: =M5*(1-'Financial information FT'!$B$36) -> 3220.5286 | N55: =SUM(B55:M55) -> 27493.317
A56: satisfied demand | B56: =B55 -> 1442.8488 | C56: =C55 -> 1700.9953 | D56: =D55 -> 1700.9953 | E56: =E55 -> 1959.1419 | F56: =F55 -> 1959.1419 | G56: =G55 -> 2704.2355 | H56: =H55 -> 2704.2355 | I56: =I55 -> 1959.1419 | ... M56: =M55 -> 3220.5286 | N56: =SUM(B56:M56) -> 27493.317
A57: Extra donuts(over) | B57: =IF(B55<$E$2,$E$2-B55,0) -> 0 | C57: =IF(C55<$E$2,$E$2-C55,0) -> 0 | D57: =IF(D55<$E$2,$E$2-D55,0) -> 0 | E57: =IF(E55<$E$2,$E$2-E55,0) -> 0 | F57: =IF(F55<$E$2,$E$2-F55,0) -> 0 | G57: =IF(G55<$E$2,$E$2-G55,0) -> 0 | H57: =IF(H55<$E$2,$E$2-H55,0) -> 0 | I57: =IF(I55<$E$2,$E$2-I55,0) -> 0 | ... M57: =IF(M55<$E$2,$E$2-M55,0) -> 0 | N57: =SUM(B57:M57) -> 0
A58: Unsatisfied customers (short) | B58: =0 -> 0 | C58: =0 -> 0 | D58: =0 -> 0 | E58: =0 -> 0 | F58: =0 -> 0 | G58: =0 -> 0 | H58: =0 -> 0 | I58: =0 -> 0 | ... M58: =0 -> 0 | N58: =SUM(B58:M58) -> 0
A59: Revenue
A60: coffee | B60: =B56*GETPIVOTDATA("Expense/revenue FT",'Financial information FT'!$I$4,"Profit Model label","Rev: Coffee") -> 4314.1178 | C60: =C56*GETPIVOTDATA("Expense/revenue FT",'Financial information FT'!$I$4,"Profit Model label","Rev: Coffee") -> 5085.976 | D60: =D56*GETPIVOTDATA("Expense/revenue FT",'Financial information FT'!$I$4,"Profit Model label","Rev: Coffee") -> 5085.976 | E60: =E56*GETPIVOTDATA("Expense/revenue FT",'Financial information FT'!$I$4,"Profit Model label","Rev: Coffee") -> 5857.8343 | F60: =F56*GETPIVOTDATA("Expense/revenue FT",'Financial information FT'!$I$4,"Profit Model label","Rev: Coffee") -> 5857.8343 | G60: =G56*GETPIVOTDATA("Expense/revenue FT",'Financial information FT'!$I$4,"Profit Model label","Rev: Coffee") -> 8085.6641 | H60: =H56*GETPIVOTDATA("Expense/revenue FT",'Financial information FT'!$I$4,"Profit Model label","Rev: Coffee") -> 8085.6641 | I60: =I56*GETPIVOTDATA("Expense/revenue FT",'Financial information FT'!$I$4,"Profit Model label","Rev: Coffee") -> 5857.8343 | ... M60: =M56*GETPIVOTDATA("Expense/revenue FT",'Financial information FT'!$I$4,"Profit Model label","Rev: Coffee") -> 9629.3806 | N60: =SUM(B60:M60) -> 82205.019
A61: donut | B61: =B56*GETPIVOTDATA("Expense/revenue FT",'Financial information FT'!$I$4,"Profit Model label","Rev: Donut") -> 3607.1219 | C61: =C56*GETPIVOTDATA("Expense/revenue FT",'Financial information FT'!$I$4,"Profit Model label","Rev: Donut") -> 4252.4883 | D61: =D56*GETPIVOTDATA("Expense/revenue FT",'Financial information FT'!$I$4,"Profit Model label","Rev: Donut") -> 4252.4883 | E61: =E56*GETPIVOTDATA("Expense/revenue FT",'Financial information FT'!$I$4,"Profit Model label","Rev: Donut") -> 4897.8547 | F61: =F56*GETPIVOTDATA("Expense/revenue FT",'Financial information FT'!$I$4,"Profit Model label","Rev: Donut") -> 4897.8547 | G61: =G56*GETPIVOTDATA("Expense/revenue FT",'Financial information FT'!$I$4,"Profit Model label","Rev: Donut") -> 6760.5887 | H61: =H56*GETPIVOTDATA("Expense/revenue FT",'Financial information FT'!$I$4,"Profit Model label","Rev: Donut") -> 6760.5887 | I61: =I56*GETPIVOTDATA("Expense/revenue FT",'Financial information FT'!$I$4,"Profit Model label","Rev: Donut") -> 4897.8547 | ... M61: =M56*GETPIVOTDATA("Expense/revenue FT",'Financial information FT'!$I$4,"Profit Model label","Rev: Donut") -> 8051.3215 | N61: =SUM(B61:M61) -> 68733.293
A62: Revenue from day old sales | B62: =B57*$G$2 -> 0 | C62: =C57*$G$2 -> 0 | D62: =D57*$G$2 -> 0 | E62: =E57*$G$2 -> 0 | F62: =F57*$G$2 -> 0 | G62: =G57*$G$2 -> 0 | H62: =H57*$G$2 -> 0 | I62: =I57*$G$2 -> 0 | ... M62: =M57*$G$2 -> 0 | N62: =SUM(B62:M62) -> 0
A63: Total Revenue | B63: =SUM(B60:B62) -> 7921.2397 | C63: =SUM(C60:C62) -> 9338.4644 | D63: =SUM(D60:D62) -> 9338.4644 | E63: =SUM(E60:E62) -> 10755.689 | F63: =SUM(F60:F62) -> 10755.689 | G63: =SUM(G60:G62) -> 14846.253 | H63: =SUM(H60:H62) -> 14846.253 | I63: =SUM(I60:I62) -> 10755.689 | ... M63: =SUM(M60:M62) -> 17680.702 | N63: =SUM(B63:M63) -> 150938.31
A64: Expenses
A65: Fixed Expenses | B65: =GETPIVOTDATA("Expense/revenue FT",'Financial information FT'!$I$4,"Profit Model label","Fixed Expense") -> 5045 | C65: =GETPIVOTDATA("Expense/revenue FT",'Financial information FT'!$I$4,"Profit Model label","Fixed Expense") -> 5045 | D65: =GETPIVOTDATA("Expense/revenue FT",'Financial information FT'!$I$4,"Profit Model label","Fixed Expense") -> 5045 | E65: =GETPIVOTDATA("Expense/revenue FT",'Financial information FT'!$I$4,"Profit Model label","Fixed Expense") -> 5045 | F65: =GETPIVOTDATA("Expense/revenue FT",'Financial information FT'!$I$4,"Profit Model label","Fixed Expense") -> 5045 | G65: =GETPIVOTDATA("Expense/revenue FT",'Financial information FT'!$I$4,"Profit Model label","Fixed Expense") -> 5045 | H65: =GETPIVOTDATA("Expense/revenue FT",'Financial information FT'!$I$4,"Profit Model label","Fixed Expense") -> 5045 | I65: =GETPIVOTDATA("Expense/revenue FT",'Financial information FT'!$I$4,"Profit Model label","Fixed Expense") -> 5045 | ... M65: =GETPIVOTDATA("Expense/revenue FT",'Financial information FT'!$I$4,"Profit Model label","Fixed Expense") -> 5045 | N65: =SUM(B65:M65) -> 60540
A66: Total Fixed Expense | B66: =B65 -> 5045 | C66: =C65 -> 5045 | D66: =D65 -> 5045 | E66: =E65 -> 5045 | F66: =F65 -> 5045 | G66: =G65 -> 5045 | H66: =H65 -> 5045 | I66: =I65 -> 5045 | ... M66: =M65 -> 5045 | N66: =SUM(B66:M66) -> 60540
A68: Variable Expenses
A69: Coffee Variable expense | B69: =GETPIVOTDATA("Expense/revenue FT",'Financial information FT'!$I$4,"Profit Model label","Variable Expense coffee")*B56 -> 721.42438 | C69: =GETPIVOTDATA("Expense/revenue FT",'Financial information FT'!$I$4,"Profit Model label","Variable Expense coffee")*C56 -> 850.49766 | D69: =GETPIVOTDATA("Expense/revenue FT",'Financial information FT'!$I$4,"Profit Model label","Variable Expense coffee")*D56 -> 850.49766 | E69: =GETPIVOTDATA("Expense/revenue FT",'Financial information FT'!$I$4,"Profit Model label","Variable Expense coffee")*E56 -> 979.57095 | F69: =GETPIVOTDATA("Expense/revenue FT",'Financial information FT'!$I$4,"Profit Model label","Variable Expense coffee")*F56 -> 979.57095 | G69: =GETPIVOTDATA("Expense/revenue FT",'Financial information FT'!$I$4,"Profit Model label","Variable Expense coffee")*G56 -> 1352.1177 | H69: =GETPIVOTDATA("Expense/revenue FT",'Financial information FT'!$I$4,"Profit Model label","Variable Expense coffee")*H56 -> 1352.1177 | I69: =GETPIVOTDATA("Expense/revenue FT",'Financial information FT'!$I$4,"Profit Model label","Variable Expense coffee")*I56 -> 979.57095 | ... M69: =GETPIVOTDATA("Expense/revenue FT",'Financial information FT'!$I$4,"Profit Model label","Variable Expense coffee")*M56 -> 1610.2643 | N69: =SUM(B69:M69) -> 13746.659
A70: Donut Variable expense | B70: =GETPIVOTDATA("Expense/revenue FT",'Financial information FT'!$I$4,"Profit Model label","Variable Expense donut")*B56 -> 865.70926 | C70: =GETPIVOTDATA("Expense/revenue FT",'Financial information FT'!$I$4,"Profit Model label","Variable Expense donut")*C56 -> 1020.5972 | D70: =GETPIVOTDATA("Expense/revenue FT",'Financial information FT'!$I$4,"Profit Model label","Variable Expense donut")*D56 -> 1020.5972 | E70: =GETPIVOTDATA("Expense/revenue FT",'Financial information FT'!$I$4,"Profit Model label","Variable Expense donut")*E56 -> 1175.4851 | F70: =GETPIVOTDATA("Expense/revenue FT",'Financial information FT'!$I$4,"Profit Model label","Variable Expense donut")*F56 -> 1175.4851 | G70: =GETPIVOTDATA("Expense/revenue FT",'Financial information FT'!$I$4,"Profit Model label","Variable Expense donut")*G56 -> 1622.5413 | H70: =GETPIVOTDATA("Expense/revenue FT",'Financial information FT'!$I$4,"Profit Model label","Variable Expense donut")*H56 -> 1622.5413 | I70: =GETPIVOTDATA("Expense/revenue FT",'Financial information FT'!$I$4,"Profit Model label","Variable Expense donut")*I56 -> 1175.4851 | ... M70: =GETPIVOTDATA("Expense/revenue FT",'Financial information FT'!$I$4,"Profit Model label","Variable Expense donut")*M56 -> 1932.3172 | N70: =SUM(B70:M70) -> 16495.99
A71: Total Variable Expenses | B71: =SUM(B69:B70) -> 1587.1336 | C71: =SUM(C69:C70) -> 1871.0949 | D71: =SUM(D69:D70) -> 1871.0949 | E71: =SUM(E69:E70) -> 2155.0561 | F71: =SUM(F69:F70) -> 2155.0561 | G71: =SUM(G69:G70) -> 2974.659 | H71: =SUM(H69:H70) -> 2974.659 | I71: =SUM(I69:I70) -> 2155.0561 | ... M71: =SUM(M69:M70) -> 3542.5815 | N71: =SUM(B71:M71) -> 30242.649
A72: Expenses: due to lost sales | B72: =0 -> 0 | C72: =0 -> 0 | D72: =0 -> 0 | E72: =0 -> 0 | F72: =0 -> 0 | G72: =0 -> 0 | H72: =0 -> 0 | I72: =0 -> 0 | ... N72: =0 -> 0
A73: Total Expenses | B73: =B66+B71+B72 -> 6632.1336 | C73: =C66+C71+C72 -> 6916.0949 | D73: =D66+D71+D72 -> 6916.0949 | E73: =E66+E71+E72 -> 7200.0561 | F73: =F66+F71+F72 -> 7200.0561 | G73: =G66+G71+G72 -> 8019.659 | H73: =H66+H71+H72 -> 8019.659 | I73: =I66+I71+I72 -> 7200.0561 | ... M73: =M66+M71+M72 -> 8587.5815 | N73: =SUM(B73:M73) -> 90782.649
A75: Profit Donuts and Coffee | B75: =B63-B73 -> 1289.1061 | C75: =C63-C73 -> 2422.3695 | D75: =D63-D73 -> 2422.3695 | E75: =E63-E73 -> 3555.6329 | F75: =F63-F73 -> 3555.6329 | G75: =G63-G73 -> 6826.5937 | H75: =H63-H73 -> 6826.5937 | I75: =I63-I73 -> 3555.6329 | ... M75: =M63-M73 -> 9093.1206 | N75: =SUM(B75:M75) -> 60155.663
